{
	"song": {
		"speed": 2.7,
		"stage": "illusion-stage",
		"player1": "neo-whitty",
		"player2": "neo-monster",
		"player3": null,
		"events": [
			[
				10666.6666666667,
				[
					[
						"Lyrics",
						"Well, look at this!",
						"0x00F0FC"
					]
				]
			],
			[
				11666.6666666667,
				[
					[
						"Lyrics",
						"all the children in one place now",
						"0x00F0FC"
					]
				]
			],
			[
				13333.3333333333,
				[
					[
						"Lyrics",
						"",
						"0x00F0FC"
					]
				]
			],
			[
				16000,
				[
					[
						"Lyrics",
						"hope",
						"0x00F0FC"
					]
				]
			],
			[
				16333.3333333333,
				[
					[
						"Lyrics",
						"hope you",
						"0x00F0FC"
					]
				]
			],
			[
				16666.6666666667,
				[
					[
						"Lyrics",
						"hope you mind",
						"0x00F0FC"
					]
				]
			],
			[
				17000,
				[
					[
						"Lyrics",
						"hope you mind if",
						"0x00F0FC"
					]
				]
			],
			[
				17333.3333333333,
				[
					[
						"Lyrics",
						"i",
						"0x00F0FC"
					]
				]
			],
			[
				17666.6666666667,
				[
					[
						"Lyrics",
						"i up",
						"0x00F0FC"
					]
				]
			],
			[
				18000,
				[
					[
						"Lyrics",
						"i upstage",
						"0x00F0FC"
					]
				]
			],
			[
				18333.3333333333,
				[
					[
						"Lyrics",
						"i upstage you!",
						"0x00F0FC"
					]
				]
			],
			[
				18666.6666666667,
				[
					[
						"Lyrics",
						"",
						"0x00F0FC"
					]
				]
			],
			[
				21333.3333333333,
				[
					[
						"Lyrics",
						"thought",
						"0x00F0FC"
					]
				]
			],
			[
				21666.6666666667,
				[
					[
						"Lyrics",
						"thought i'd drop by",
						"0x00F0FC"
					]
				]
			],
			[
				22333.3333333333,
				[
					[
						"Lyrics",
						"to lay your careers to waster now",
						"0x00F0FC"
					]
				]
			],
			[
				24000,
				[
					[
						"Lyrics",
						"",
						"0x00F0FC"
					]
				]
			],
			[
				26666.6666666667,
				[
					[
						"Lyrics",
						"tear",
						"0x00F0FC"
					]
				]
			],
			[
				26916.6666666667,
				[
					[
						"Lyrics",
						"tear your",
						"0x00F0FC"
					]
				]
			],
			[
				27083.3333333333,
				[
					[
						"Lyrics",
						"tear your a",
						"0x00F0FC"
					]
				]
			],
			[
				27333.3333333333,
				[
					[
						"Lyrics",
						"tear your apart,",
						"0x00F0FC"
					]
				]
			],
			[
				27583.3333333333,
				[
					[
						"Lyrics",
						"rip",
						"0x00F0FC"
					]
				]
			],
			[
				27750,
				[
					[
						"Lyrics",
						"rip out",
						"0x00F0FC"
					]
				]
			],
			[
				28000,
				[
					[
						"Lyrics",
						"rip out your",
						"0x00F0FC"
					]
				]
			],
			[
				28250,
				[
					[
						"Lyrics",
						"rip out your mu",
						"0x00F0FC"
					]
				]
			],
			[
				28416.6666666667,
				[
					[
						"Lyrics",
						"rip out your music's",
						"0x00F0FC"
					]
				]
			],
			[
				28666.6666666667,
				[
					[
						"Lyrics",
						"rip out your music's heart",
						"0x00F0FC"
					]
				]
			],
			[
				28916.6666666667,
				[
					[
						"Lyrics",
						"rip out your music's heart and",
						"0x00F0FC"
					]
				]
			],
			[
				29083.3333333333,
				[
					[
						"Lyrics",
						"rip out your music's heart and rip",
						"0x00F0FC"
					]
				]
			],
			[
				29333.3333333333,
				[
					[
						"Lyrics",
						"rip out your music's heart and rip out",
						"0x00F0FC"
					]
				]
			],
			[
				30000,
				[
					[
						"Lyrics",
						"All",
						"0x00F0FC"
					]
				]
			],
			[
				30333.3333333333,
				[
					[
						"Lyrics",
						"All your",
						"0x00F0FC"
					]
				]
			],
			[
				30666.6666666667,
				[
					[
						"Lyrics",
						"All your real",
						"0x00F0FC"
					]
				]
			],
			[
				31000,
				[
					[
						"Lyrics",
						"All your real hearts",
						"0x00F0FC"
					]
				]
			],
			[
				31333.3333333333,
				[
					[
						"Lyrics",
						"All your real hearts too",
						"0x00F0FC"
					]
				]
			],
			[
				32000,
				[
					[
						"Lyrics",
						"this",
						"0x00F0FC"
					]
				]
			],
			[
				32500,
				[
					[
						"Lyrics",
						"this world",
						"0x00F0FC"
					]
				]
			],
			[
				33000,
				[
					[
						"Lyrics",
						"this world grown",
						"0x00F0FC"
					]
				]
			],
			[
				33166.6666666667,
				[
					[
						"Lyrics",
						"this world grown so",
						"0x00F0FC"
					]
				]
			],
			[
				33333.3333333333,
				[
					[
						"Lyrics",
						"this world grown so tooth",
						"0x00F0FC"
					]
				]
			],
			[
				33500,
				[
					[
						"Lyrics",
						"this world grown so toothless",
						"0x00F0FC"
					]
				]
			],
			[
				33666.6666666667,
				[
					[
						"Lyrics",
						"this world grown so toothless and",
						"0x00F0FC"
					]
				]
			],
			[
				33833.3333333333,
				[
					[
						"Lyrics",
						"this world grown so toothless and tame",
						"0x00F0FC"
					]
				]
			],
			[
				34333.3333333333,
				[
					[
						"Lyrics",
						"it's",
						"0x00F0FC"
					]
				]
			],
			[
				34500,
				[
					[
						"Lyrics",
						"it's re",
						"0x00F0FC"
					]
				]
			],
			[
				34666.6666666667,
				[
					[
						"Lyrics",
						"it's repla",
						"0x00F0FC"
					]
				]
			],
			[
				34916.6666666667,
				[
					[
						"Lyrics",
						"it's replacing",
						"0x00F0FC"
					]
				]
			],
			[
				35166.6666666667,
				[
					[
						"Lyrics",
						"it's replacing the",
						"0x00F0FC"
					]
				]
			],
			[
				35333.3333333333,
				[
					[
						"Lyrics",
						"it's replacing the mons",
						"0x00F0FC"
					]
				]
			],
			[
				35666.6666666667,
				[
					[
						"Lyrics",
						"it's replacing the monster",
						"0x00F0FC"
					]
				]
			],
			[
				35833.3333333333,
				[
					[
						"Lyrics",
						"that",
						"0x00F0FC"
					]
				]
			],
			[
				36000,
				[
					[
						"Lyrics",
						"that made",
						"0x00F0FC"
					]
				]
			],
			[
				36166.6666666667,
				[
					[
						"Lyrics",
						"that made an",
						"0x00F0FC"
					]
				]
			],
			[
				36333.3333333333,
				[
					[
						"Lyrics",
						"that made an art",
						"0x00F0FC"
					]
				]
			],
			[
				36500,
				[
					[
						"Lyrics",
						"that made an art of",
						"0x00F0FC"
					]
				]
			],
			[
				36666.6666666667,
				[
					[
						"Lyrics",
						"that made an art of kill",
						"0x00F0FC"
					]
				]
			],
			[
				37000,
				[
					[
						"Lyrics",
						"that made an art of killing",
						"0x00F0FC"
					]
				]
			],
			[
				37333.3333333333,
				[
					[
						"Lyrics",
						"",
						"0x00F0FC"
					]
				]
			],
			[
				42666.6666666667,
				[
					[
						"Lyrics",
						"they'll",
						"0x00F0FC"
					]
				]
			],
			[
				44000,
				[
					[
						"Lyrics",
						"they'll know",
						"0x00F0FC"
					]
				]
			],
			[
				44666.6666666667,
				[
					[
						"Lyrics",
						"they'll know my",
						"0x00F0FC"
					]
				]
			],
			[
				45333.3333333333,
				[
					[
						"Lyrics",
						"they'll know my name",
						"0x00F0FC"
					]
				]
			],
			[
				46666.6666666667,
				[
					[
						"Lyrics",
						"when",
						"0x00F0FC"
					]
				]
			],
			[
				47333.3333333333,
				[
					[
						"Lyrics",
						"when their",
						"0x00F0FC"
					]
				]
			],
			[
				48000,
				[
					[
						"Lyrics",
						"when their heart",
						"0x00F0FC"
					]
				]
			],
			[
				49333.3333333334,
				[
					[
						"Lyrics",
						"when their heart beat",
						"0x00F0FC"
					]
				]
			],
			[
				50666.6666666667,
				[
					[
						"Lyrics",
						"still",
						"0x00F0FC"
					]
				]
			],
			[
				52000,
				[
					[
						"Lyrics",
						"stilling",
						"0x00F0FC"
					]
				]
			],
			[
				53333.3333333334,
				[
					[
						"Lyrics",
						"...",
						"0x00F0FC"
					]
				]
			],
			[
				64000,
				[
					[
						"Lyrics",
						"what have you got",
						"0x00F0FC"
					]
				]
			],
			[
				65000,
				[
					[
						"Lyrics",
						"just a couple corny jumpscare?",
						"0x00F0FC"
					]
				]
			],
			[
				66666.6666666667,
				[
					[
						"Lyrics",
						"",
						"0x00F0FC"
					]
				]
			],
			[
				69333.3333333334,
				[
					[
						"Lyrics",
						"scream",
						"0x00F0FC"
					]
				]
			],
			[
				69666.6666666667,
				[
					[
						"Lyrics",
						"screaming",
						"0x00F0FC"
					]
				]
			],
			[
				70000,
				[
					[
						"Lyrics",
						"screaming for",
						"0x00F0FC"
					]
				]
			],
			[
				70333.3333333334,
				[
					[
						"Lyrics",
						"screaming for a",
						"0x00F0FC"
					]
				]
			],
			[
				70666.6666666667,
				[
					[
						"Lyrics",
						"se",
						"0x00F0FC"
					]
				]
			],
			[
				71000,
				[
					[
						"Lyrics",
						"second's",
						"0x00F0FC"
					]
				]
			],
			[
				71333.3333333334,
				[
					[
						"Lyrics",
						"second's no",
						"0x00F0FC"
					]
				]
			],
			[
				71666.6666666667,
				[
					[
						"Lyrics",
						"second's no time",
						"0x00F0FC"
					]
				]
			],
			[
				72000,
				[
					[
						"Lyrics",
						"",
						"0x00F0FC"
					]
				]
			],
			[
				74666.6666666667,
				[
					[
						"Lyrics",
						"terror comes from knowing your demise",
						"0x00F0FC"
					]
				]
			],
			[
				76333.3333333333,
				[
					[
						"Lyrics",
						"is waiting for everywhere",
						"0x00F0FC"
					]
				]
			],
			[
				77333.3333333333,
				[
					[
						"Lyrics",
						"",
						"0x00F0FC"
					]
				]
			],
			[
				80000,
				[
					[
						"Lyrics",
						"but",
						"0x00F0FC"
					]
				]
			],
			[
				80250,
				[
					[
						"Lyrics",
						"but don't",
						"0x00F0FC"
					]
				]
			],
			[
				80500,
				[
					[
						"Lyrics",
						"but don't you",
						"0x00F0FC"
					]
				]
			],
			[
				80666.6666666667,
				[
					[
						"Lyrics",
						"but don't you wo",
						"0x00F0FC"
					]
				]
			],
			[
				80916.6666666667,
				[
					[
						"Lyrics",
						"but don't you worry",
						"0x00F0FC"
					]
				]
			],
			[
				81166.6666666667,
				[
					[
						"Lyrics",
						"wont",
						"0x00F0FC"
					]
				]
			],
			[
				81333.3333333333,
				[
					[
						"Lyrics",
						"wont see",
						"0x00F0FC"
					]
				]
			],
			[
				81583.3333333333,
				[
					[
						"Lyrics",
						"wont see you",
						"0x00F0FC"
					]
				]
			],
			[
				81833.3333333333,
				[
					[
						"Lyrics",
						"wont see you end",
						"0x00F0FC"
					]
				]
			],
			[
				82000,
				[
					[
						"Lyrics",
						"wont see you end co",
						"0x00F0FC"
					]
				]
			],
			[
				82250,
				[
					[
						"Lyrics",
						"wont see you end coming",
						"0x00F0FC"
					]
				]
			],
			[
				82500,
				[
					[
						"Lyrics",
						"wont see you end coming when",
						"0x00F0FC"
					]
				]
			],
			[
				82666.6666666667,
				[
					[
						"Lyrics",
						"your",
						"0x00F0FC"
					]
				]
			],
			[
				84000,
				[
					[
						"Lyrics",
						"your eyes",
						"0x00F0FC"
					]
				]
			],
			[
				84666.6666666667,
				[
					[
						"Lyrics",
						"your eyes are",
						"0x00F0FC"
					]
				]
			],
			[
				85333.3333333333,
				[
					[
						"Lyrics",
						"mine!!!",
						"0x00F0FC"
					]
				]
			],
			[
				87166.6666666666,
				[
					[
						"Lyrics",
						"",
						"0x00F0FC"
					]
				]
			]
		],
		"notes": [],
		"splashSkin": null,
		"validScore": false,
		"gfVersion": "kaity",
		"bpm": 180,
		"arrowSkin": null,
		"needsVoices": true,
		"song": "illusion"
	}
}