<?xml version="1.0" encoding="utf-8"?>
<TextureAtlas imagePath="Hex_Maniac.png">
	<!-- Created with Adobe Animate version 20.0.3.25487 -->
	<!-- http://www.adobe.com/products/animate.html -->
	<SubTexture name="ManiacDown0000" x="0" y="0" width="449" height="419" frameX="0" frameY="0" frameWidth="449" frameHeight="419"/>
	<SubTexture name="ManiacDown0001" x="0" y="0" width="449" height="419" frameX="0" frameY="0" frameWidth="449" frameHeight="419"/>
	<SubTexture name="ManiacDown0002" x="450" y="0" width="449" height="419" frameX="0" frameY="0" frameWidth="449" frameHeight="419"/>
	<SubTexture name="ManiacDown0003" x="900" y="0" width="449" height="419" frameX="0" frameY="0" frameWidth="449" frameHeight="419"/>
	<SubTexture name="ManiacDown0004" x="1350" y="0" width="449" height="419" frameX="0" frameY="0" frameWidth="449" frameHeight="419"/>
	<SubTexture name="ManiacDown0005" x="1800" y="0" width="449" height="419" frameX="0" frameY="0" frameWidth="449" frameHeight="419"/>
	<SubTexture name="ManiacDown0006" x="1800" y="0" width="449" height="419" frameX="0" frameY="0" frameWidth="449" frameHeight="419"/>
	<SubTexture name="ManiacDown0007" x="1800" y="0" width="449" height="419" frameX="0" frameY="0" frameWidth="449" frameHeight="419"/>
	<SubTexture name="ManiacDown0008" x="1800" y="0" width="449" height="419" frameX="0" frameY="0" frameWidth="449" frameHeight="419"/>
	<SubTexture name="ManiacDown0009" x="1800" y="0" width="449" height="419" frameX="0" frameY="0" frameWidth="449" frameHeight="419"/>
	<SubTexture name="ManiacDown0010" x="1800" y="0" width="449" height="419" frameX="0" frameY="0" frameWidth="449" frameHeight="419"/>
	<SubTexture name="ManiacDown0011" x="1800" y="0" width="449" height="419" frameX="0" frameY="0" frameWidth="449" frameHeight="419"/>
	<SubTexture name="ManiacDown0012" x="1800" y="0" width="449" height="419" frameX="0" frameY="0" frameWidth="449" frameHeight="419"/>
	<SubTexture name="ManiacDown0013" x="1800" y="0" width="449" height="419" frameX="0" frameY="0" frameWidth="449" frameHeight="419"/>
	<SubTexture name="ManiacIdle_Loop0000" x="2250" y="0" width="473" height="456" frameX="0" frameY="0" frameWidth="473" frameHeight="456"/>
	<SubTexture name="ManiacIdle_Loop0001" x="2250" y="0" width="473" height="456" frameX="0" frameY="0" frameWidth="473" frameHeight="456"/>
	<SubTexture name="ManiacIdle_Loop0002" x="0" y="420" width="473" height="456" frameX="0" frameY="0" frameWidth="473" frameHeight="456"/>
	<SubTexture name="ManiacIdle_Loop0003" x="0" y="420" width="473" height="456" frameX="0" frameY="0" frameWidth="473" frameHeight="456"/>
	<SubTexture name="ManiacIdle_Loop0004" x="474" y="420" width="473" height="456" frameX="0" frameY="0" frameWidth="473" frameHeight="456"/>
	<SubTexture name="ManiacIdle_Loop0005" x="474" y="420" width="473" height="456" frameX="0" frameY="0" frameWidth="473" frameHeight="456"/>
	<SubTexture name="ManiacIdle_Loop0006" x="948" y="420" width="473" height="456" frameX="0" frameY="0" frameWidth="473" frameHeight="456"/>
	<SubTexture name="ManiacIdle_Loop0007" x="948" y="420" width="473" height="456" frameX="0" frameY="0" frameWidth="473" frameHeight="456"/>
	<SubTexture name="ManiacIdle_Loop0008" x="1422" y="420" width="473" height="456" frameX="0" frameY="0" frameWidth="473" frameHeight="456"/>
	<SubTexture name="ManiacIdle_Loop0009" x="1422" y="420" width="473" height="456" frameX="0" frameY="0" frameWidth="473" frameHeight="456"/>
	<SubTexture name="ManiacIdle_Loop0010" x="1896" y="457" width="473" height="456" frameX="0" frameY="0" frameWidth="473" frameHeight="456"/>
	<SubTexture name="ManiacIdle_Loop0011" x="1896" y="457" width="473" height="456" frameX="0" frameY="0" frameWidth="473" frameHeight="456"/>
	<SubTexture name="ManiacIdle_Loop0012" x="2370" y="457" width="473" height="456" frameX="0" frameY="0" frameWidth="473" frameHeight="456"/>
	<SubTexture name="ManiacIdle_Loop0013" x="2370" y="457" width="473" height="456" frameX="0" frameY="0" frameWidth="473" frameHeight="456"/>
	<SubTexture name="ManiacIdle_Loop0014" x="0" y="877" width="473" height="456" frameX="0" frameY="0" frameWidth="473" frameHeight="456"/>
	<SubTexture name="ManiacIdle_Loop0015" x="0" y="877" width="473" height="456" frameX="0" frameY="0" frameWidth="473" frameHeight="456"/>
	<SubTexture name="ManiacIdle_Loop0016" x="474" y="877" width="473" height="456" frameX="0" frameY="0" frameWidth="473" frameHeight="456"/>
	<SubTexture name="ManiacIdle_Loop0017" x="474" y="877" width="473" height="456" frameX="0" frameY="0" frameWidth="473" frameHeight="456"/>
	<SubTexture name="ManiacIdle0000" x="948" y="877" width="466" height="456" frameX="0" frameY="0" frameWidth="466" frameHeight="456"/>
	<SubTexture name="ManiacIdle0001" x="948" y="877" width="466" height="456" frameX="0" frameY="0" frameWidth="466" frameHeight="456"/>
	<SubTexture name="ManiacIdle0002" x="1415" y="877" width="466" height="456" frameX="0" frameY="0" frameWidth="466" frameHeight="456"/>
	<SubTexture name="ManiacIdle0003" x="1415" y="877" width="466" height="456" frameX="0" frameY="0" frameWidth="466" frameHeight="456"/>
	<SubTexture name="ManiacIdle0004" x="1882" y="914" width="466" height="456" frameX="0" frameY="0" frameWidth="466" frameHeight="456"/>
	<SubTexture name="ManiacIdle0005" x="1882" y="914" width="466" height="456" frameX="0" frameY="0" frameWidth="466" frameHeight="456"/>
	<SubTexture name="ManiacIdle0006" x="2349" y="914" width="466" height="456" frameX="0" frameY="0" frameWidth="466" frameHeight="456"/>
	<SubTexture name="ManiacIdle0007" x="2349" y="914" width="466" height="456" frameX="0" frameY="0" frameWidth="466" frameHeight="456"/>
	<SubTexture name="ManiacIdle0008" x="0" y="1334" width="466" height="456" frameX="0" frameY="0" frameWidth="466" frameHeight="456"/>
	<SubTexture name="ManiacIdle0009" x="0" y="1334" width="466" height="456" frameX="0" frameY="0" frameWidth="466" frameHeight="456"/>
	<SubTexture name="ManiacIdle0010" x="467" y="1334" width="466" height="456" frameX="0" frameY="0" frameWidth="466" frameHeight="456"/>
	<SubTexture name="ManiacIdle0011" x="467" y="1334" width="466" height="456" frameX="0" frameY="0" frameWidth="466" frameHeight="456"/>
	<SubTexture name="ManiacIdle0012" x="934" y="1334" width="466" height="456" frameX="0" frameY="0" frameWidth="466" frameHeight="456"/>
	<SubTexture name="ManiacIdle0013" x="934" y="1334" width="466" height="456" frameX="0" frameY="0" frameWidth="466" frameHeight="456"/>
	<SubTexture name="ManiacIdle0014" x="1401" y="1334" width="466" height="456" frameX="0" frameY="0" frameWidth="466" frameHeight="456"/>
	<SubTexture name="ManiacIdle0015" x="1401" y="1334" width="466" height="456" frameX="0" frameY="0" frameWidth="466" frameHeight="456"/>
	<SubTexture name="ManiacIdle0016" x="1868" y="1371" width="466" height="456" frameX="0" frameY="0" frameWidth="466" frameHeight="456"/>
	<SubTexture name="ManiacIdle0017" x="1868" y="1371" width="466" height="456" frameX="0" frameY="0" frameWidth="466" frameHeight="456"/>
	<SubTexture name="ManiacLeft0000" x="2335" y="1371" width="428" height="451" frameX="0" frameY="0" frameWidth="428" frameHeight="451"/>
	<SubTexture name="ManiacLeft0001" x="2335" y="1371" width="428" height="451" frameX="0" frameY="0" frameWidth="428" frameHeight="451"/>
	<SubTexture name="ManiacLeft0002" x="0" y="1791" width="428" height="451" frameX="0" frameY="0" frameWidth="428" frameHeight="451"/>
	<SubTexture name="ManiacLeft0003" x="429" y="1791" width="428" height="451" frameX="0" frameY="0" frameWidth="428" frameHeight="451"/>
	<SubTexture name="ManiacLeft0004" x="858" y="1791" width="428" height="451" frameX="0" frameY="0" frameWidth="428" frameHeight="451"/>
	<SubTexture name="ManiacLeft0005" x="1287" y="1791" width="428" height="451" frameX="0" frameY="0" frameWidth="428" frameHeight="451"/>
	<SubTexture name="ManiacLeft0006" x="1716" y="1828" width="428" height="451" frameX="0" frameY="0" frameWidth="428" frameHeight="451"/>
	<SubTexture name="ManiacLeft0007" x="1716" y="1828" width="428" height="451" frameX="0" frameY="0" frameWidth="428" frameHeight="451"/>
	<SubTexture name="ManiacLeft0008" x="1716" y="1828" width="428" height="451" frameX="0" frameY="0" frameWidth="428" frameHeight="451"/>
	<SubTexture name="ManiacLeft0009" x="1716" y="1828" width="428" height="451" frameX="0" frameY="0" frameWidth="428" frameHeight="451"/>
	<SubTexture name="ManiacLeft0010" x="1716" y="1828" width="428" height="451" frameX="0" frameY="0" frameWidth="428" frameHeight="451"/>
	<SubTexture name="ManiacLeft0011" x="1716" y="1828" width="428" height="451" frameX="0" frameY="0" frameWidth="428" frameHeight="451"/>
	<SubTexture name="ManiacLeft0012" x="1716" y="1828" width="428" height="451" frameX="0" frameY="0" frameWidth="428" frameHeight="451"/>
	<SubTexture name="ManiacLeft0013" x="1716" y="1828" width="428" height="451" frameX="0" frameY="0" frameWidth="428" frameHeight="451"/>
	<SubTexture name="ManiacRight0000" x="2145" y="1828" width="445" height="434" frameX="0" frameY="0" frameWidth="445" frameHeight="434"/>
	<SubTexture name="ManiacRight0001" x="2145" y="1828" width="445" height="434" frameX="0" frameY="0" frameWidth="445" frameHeight="434"/>
	<SubTexture name="ManiacRight0002" x="0" y="2243" width="445" height="434" frameX="0" frameY="0" frameWidth="445" frameHeight="434"/>
	<SubTexture name="ManiacRight0003" x="446" y="2243" width="445" height="434" frameX="0" frameY="0" frameWidth="445" frameHeight="434"/>
	<SubTexture name="ManiacRight0004" x="892" y="2243" width="445" height="434" frameX="0" frameY="0" frameWidth="445" frameHeight="434"/>
	<SubTexture name="ManiacRight0005" x="1338" y="2280" width="445" height="434" frameX="0" frameY="0" frameWidth="445" frameHeight="434"/>
	<SubTexture name="ManiacRight0006" x="1784" y="2280" width="445" height="434" frameX="0" frameY="0" frameWidth="445" frameHeight="434"/>
	<SubTexture name="ManiacRight0007" x="1784" y="2280" width="445" height="434" frameX="0" frameY="0" frameWidth="445" frameHeight="434"/>
	<SubTexture name="ManiacRight0008" x="1784" y="2280" width="445" height="434" frameX="0" frameY="0" frameWidth="445" frameHeight="434"/>
	<SubTexture name="ManiacRight0009" x="1784" y="2280" width="445" height="434" frameX="0" frameY="0" frameWidth="445" frameHeight="434"/>
	<SubTexture name="ManiacRight0010" x="1784" y="2280" width="445" height="434" frameX="0" frameY="0" frameWidth="445" frameHeight="434"/>
	<SubTexture name="ManiacRight0011" x="1784" y="2280" width="445" height="434" frameX="0" frameY="0" frameWidth="445" frameHeight="434"/>
	<SubTexture name="ManiacRight0012" x="1784" y="2280" width="445" height="434" frameX="0" frameY="0" frameWidth="445" frameHeight="434"/>
	<SubTexture name="ManiacRight0013" x="1784" y="2280" width="445" height="434" frameX="0" frameY="0" frameWidth="445" frameHeight="434"/>
	<SubTexture name="ManiacUp0000" x="2230" y="2263" width="463" height="480" frameX="0" frameY="0" frameWidth="463" frameHeight="480"/>
	<SubTexture name="ManiacUp0001" x="2230" y="2263" width="463" height="480" frameX="0" frameY="0" frameWidth="463" frameHeight="480"/>
	<SubTexture name="ManiacUp0002" x="0" y="2678" width="463" height="480" frameX="0" frameY="0" frameWidth="463" frameHeight="480"/>
	<SubTexture name="ManiacUp0003" x="464" y="2678" width="463" height="480" frameX="0" frameY="0" frameWidth="463" frameHeight="480"/>
	<SubTexture name="ManiacUp0004" x="928" y="2715" width="463" height="480" frameX="0" frameY="0" frameWidth="463" frameHeight="480"/>
	<SubTexture name="ManiacUp0005" x="1392" y="2715" width="463" height="480" frameX="0" frameY="0" frameWidth="463" frameHeight="480"/>
	<SubTexture name="ManiacUp0006" x="1856" y="2744" width="463" height="480" frameX="0" frameY="0" frameWidth="463" frameHeight="480"/>
	<SubTexture name="ManiacUp0007" x="1856" y="2744" width="463" height="480" frameX="0" frameY="0" frameWidth="463" frameHeight="480"/>
	<SubTexture name="ManiacUp0008" x="1856" y="2744" width="463" height="480" frameX="0" frameY="0" frameWidth="463" frameHeight="480"/>
	<SubTexture name="ManiacUp0009" x="1856" y="2744" width="463" height="480" frameX="0" frameY="0" frameWidth="463" frameHeight="480"/>
	<SubTexture name="ManiacUp0010" x="1856" y="2744" width="463" height="480" frameX="0" frameY="0" frameWidth="463" frameHeight="480"/>
	<SubTexture name="ManiacUp0011" x="1856" y="2744" width="463" height="480" frameX="0" frameY="0" frameWidth="463" frameHeight="480"/>
	<SubTexture name="ManiacUp0012" x="1856" y="2744" width="463" height="480" frameX="0" frameY="0" frameWidth="463" frameHeight="480"/>
	<SubTexture name="ManiacUp0013" x="1856" y="2744" width="463" height="480" frameX="0" frameY="0" frameWidth="463" frameHeight="480"/>
</TextureAtlas>