{
	"song": {
		"player1": "Sans Ex",
		"events": [],
		"gfVersion": "itsumi",
		"notes": [
			{
				"sectionNotes": [],
				"lengthInSteps": 16,
				"mustHitSection": false
			},
			{
				"sectionNotes": [
					[
						2125,
						0,
						0,
						"Mom Sing"
					],
					[
						3109.375,
						3,
						0,
						"Mom Sing"
					],
					[
						2250,
						2,
						0,
						"Mom Sing"
					],
					[
						2375,
						0,
						0,
						"Mom Sing"
					],
					[
						2500,
						1,
						0,
						"Mom Sing"
					],
					[
						2625,
						0,
						0,
						"Mom Sing"
					],
					[
						3000,
						2,
						0,
						"Mom Sing"
					],
					[
						2875,
						1,
						0,
						"Mom Sing"
					],
					[
						2937.5,
						3,
						0,
						"Mom Sing"
					],
					[
						3250,
						1,
						0,
						"Mom Sing"
					],
					[
						3875,
						0,
						0,
						"Mom Sing"
					],
					[
						3625,
						0,
						0,
						"Mom Sing"
					],
					[
						3750,
						1,
						0,
						"Mom Sing"
					],
					[
						3500,
						1,
						0,
						"Mom Sing"
					],
					[
						3375,
						3,
						0,
						"Mom Sing"
					]
				],
				"lengthInSteps": 16,
				"mustHitSection": false
			},
			{
				"sectionNotes": [
					[
						4125,
						0,
						0
					],
					[
						4250,
						2,
						0
					],
					[
						4375,
						0,
						0
					],
					[
						4500,
						1,
						0
					],
					[
						4625,
						0,
						0
					],
					[
						4875,
						1,
						0
					],
					[
						5250,
						1,
						0
					],
					[
						5500,
						1,
						0
					],
					[
						5750,
						1,
						0
					],
					[
						5625,
						0,
						0
					],
					[
						5875,
						0,
						0
					],
					[
						4940.625,
						3,
						0
					],
					[
						5109.375,
						3,
						0
					],
					[
						5000,
						2,
						0
					],
					[
						5375,
						3,
						0
					]
				],
				"lengthInSteps": 16,
				"mustHitSection": true
			},
			{
				"sectionNotes": [
					[
						6000,
						3,
						0,
						"Mom Sing"
					],
					[
						6125,
						2,
						0,
						"Mom Sing"
					],
					[
						6375,
						3,
						0,
						"Mom Sing"
					],
					[
						6500,
						1,
						0,
						"Mom Sing"
					],
					[
						6625,
						1,
						0,
						"Mom Sing"
					],
					[
						6562.5,
						3,
						0,
						"Mom Sing"
					],
					[
						6750,
						2,
						0,
						"Mom Sing"
					],
					[
						6875,
						0,
						0,
						"Mom Sing"
					],
					[
						7000,
						2,
						0,
						"Mom Sing"
					],
					[
						7500,
						2,
						0,
						"Mom Sing"
					],
					[
						7125,
						0,
						0,
						"Mom Sing"
					],
					[
						7375,
						0,
						0,
						"Mom Sing"
					],
					[
						7250,
						3,
						0,
						"Mom Sing"
					],
					[
						7750,
						1,
						0,
						"Mom Sing"
					]
				],
				"lengthInSteps": 16,
				"mustHitSection": false
			},
			{
				"sectionNotes": [
					[
						8000,
						3,
						0
					],
					[
						8125,
						2,
						0
					],
					[
						8375,
						3,
						0
					],
					[
						8500,
						1,
						0
					],
					[
						8625,
						1,
						0
					],
					[
						8543.75,
						3,
						0
					],
					[
						9000,
						2,
						0
					],
					[
						9125,
						0,
						0
					],
					[
						9375,
						0,
						0
					],
					[
						9500,
						2,
						0
					],
					[
						9750,
						1,
						0
					],
					[
						8750,
						0,
						0
					],
					[
						8875,
						1,
						0
					],
					[
						9250,
						1,
						0
					]
				],
				"lengthInSteps": 16,
				"mustHitSection": true
			},
			{
				"sectionNotes": [
					[
						10125,
						0,
						0,
						"Mom Sing"
					],
					[
						10250,
						2,
						0,
						"Mom Sing"
					],
					[
						10375,
						0,
						0,
						"Mom Sing"
					],
					[
						10500,
						1,
						0,
						"Mom Sing"
					],
					[
						10625,
						0,
						0,
						"Mom Sing"
					],
					[
						10750,
						1,
						0,
						"Mom Sing"
					],
					[
						10875,
						0,
						0,
						"Mom Sing"
					],
					[
						11000,
						3,
						0,
						"Mom Sing"
					],
					[
						11125,
						0,
						0,
						"Mom Sing"
					],
					[
						11250,
						3,
						0,
						"Mom Sing"
					],
					[
						11625,
						2,
						0,
						"Mom Sing"
					],
					[
						11500,
						0,
						0,
						"Mom Sing"
					],
					[
						11375,
						1,
						0,
						"Mom Sing"
					]
				],
				"lengthInSteps": 16,
				"mustHitSection": false
			},
			{
				"sectionNotes": [
					[
						12000,
						2,
						0
					],
					[
						12125,
						0,
						0
					],
					[
						12250,
						1,
						0
					],
					[
						12500,
						1,
						0
					],
					[
						12375,
						0,
						0
					],
					[
						12750,
						1,
						0
					],
					[
						12625,
						3,
						0
					],
					[
						12875,
						0,
						0
					],
					[
						13000,
						1,
						0
					],
					[
						13125,
						3,
						0
					],
					[
						13250,
						2,
						0
					],
					[
						13162.5,
						1,
						0
					],
					[
						13500,
						2,
						0
					],
					[
						13375,
						0,
						0
					],
					[
						13625,
						1,
						0
					],
					[
						13750,
						3,
						0
					],
					[
						13875,
						1,
						0
					]
				],
				"lengthInSteps": 16,
				"mustHitSection": true
			},
			{
				"sectionNotes": [
					[
						14000,
						4,
						0
					],
					[
						14500,
						4,
						0
					],
					[
						15000,
						4,
						0
					],
					[
						15500,
						4,
						0
					],
					[
						14000,
						3,
						0,
						"Mom Sing"
					],
					[
						14500,
						3,
						0,
						"Mom Sing"
					],
					[
						15000,
						3,
						0,
						"Mom Sing"
					],
					[
						15500,
						3,
						0,
						"Mom Sing"
					]
				],
				"lengthInSteps": 16,
				"mustHitSection": false
			},
			{
				"sectionNotes": [
					[
						16000,
						0,
						0
					],
					[
						16187.5,
						3,
						0
					],
					[
						16125,
						0,
						0
					],
					[
						16250,
						0,
						0
					],
					[
						16375,
						0,
						0
					],
					[
						16500,
						0,
						0
					],
					[
						16625,
						0,
						0
					],
					[
						16750,
						0,
						0
					],
					[
						16312.5,
						3,
						0
					],
					[
						16437.5,
						3,
						0
					],
					[
						16562.5,
						3,
						0
					],
					[
						16687.5,
						3,
						0
					],
					[
						16812.5,
						3,
						0
					],
					[
						16875,
						0,
						0
					],
					[
						16937.5,
						3,
						0
					],
					[
						17000,
						0,
						0
					],
					[
						17062.5,
						3,
						0
					],
					[
						17125,
						0,
						0
					],
					[
						16062.5,
						3,
						0
					],
					[
						16187.5,
						4,
						0,
						"Mom Sing"
					],
					[
						16062.5,
						4,
						0,
						"Mom Sing"
					],
					[
						16000,
						7,
						0,
						"Mom Sing"
					],
					[
						16125,
						7,
						0,
						"Mom Sing"
					],
					[
						16250,
						7,
						0,
						"Mom Sing"
					],
					[
						16375,
						7,
						0,
						"Mom Sing"
					],
					[
						16312.5,
						4,
						0,
						"Mom Sing"
					],
					[
						16437.5,
						4,
						0,
						"Mom Sing"
					],
					[
						16562.5,
						4,
						0,
						"Mom Sing"
					],
					[
						16687.5,
						4,
						0,
						"Mom Sing"
					],
					[
						16750,
						7,
						0,
						"Mom Sing"
					],
					[
						16625,
						7,
						0,
						"Mom Sing"
					],
					[
						16500,
						7,
						0,
						"Mom Sing"
					],
					[
						16812.5,
						4,
						0,
						"Mom Sing"
					],
					[
						16937.5,
						4,
						0,
						"Mom Sing"
					],
					[
						17062.5,
						4,
						0,
						"Mom Sing"
					],
					[
						17125,
						7,
						0,
						"Mom Sing"
					],
					[
						17000,
						7,
						0,
						"Mom Sing"
					],
					[
						16875,
						7,
						0,
						"Mom Sing"
					]
				],
				"lengthInSteps": 16,
				"mustHitSection": true
			},
			{
				"sectionNotes": [
					[
						18000,
						2,
						0
					],
					[
						18250,
						3,
						0
					],
					[
						18375,
						2,
						0
					],
					[
						18500,
						1,
						0
					],
					[
						18500,
						3,
						0
					],
					[
						18625,
						2,
						0
					],
					[
						18750,
						1,
						0
					],
					[
						18875,
						2,
						0
					],
					[
						19000,
						1,
						0
					],
					[
						19250,
						0,
						0
					],
					[
						19190.625,
						2,
						0
					],
					[
						19443.75,
						2,
						0
					],
					[
						19625,
						2,
						0
					],
					[
						19500,
						0,
						0
					],
					[
						19750,
						3,
						0
					],
					[
						19653.125,
						1,
						0
					],
					[
						19912.5,
						1,
						0
					]
				],
				"lengthInSteps": 16,
				"mustHitSection": false
			},
			{
				"sectionNotes": [
					[
						20000,
						2,
						0
					],
					[
						20250,
						3,
						0
					],
					[
						20500,
						1,
						0
					],
					[
						20375,
						2,
						0
					],
					[
						20750,
						1,
						0
					],
					[
						20534.375,
						3,
						0
					],
					[
						20650,
						2,
						0
					],
					[
						20946.875,
						3,
						0
					],
					[
						21834.375,
						0,
						0
					],
					[
						21703.125,
						3,
						0
					],
					[
						21500,
						2,
						0
					],
					[
						21000,
						0,
						0
					],
					[
						21375,
						0,
						0
					],
					[
						21200,
						1,
						0
					]
				],
				"lengthInSteps": 16,
				"mustHitSection": false
			},
			{
				"sectionNotes": [
					[
						22000,
						2,
						0
					],
					[
						22250,
						3,
						0
					],
					[
						22375,
						2,
						0
					],
					[
						22500,
						1,
						0
					],
					[
						22500,
						3,
						0
					],
					[
						22625,
						2,
						0
					],
					[
						22750,
						1,
						0
					],
					[
						22875,
						2,
						0
					],
					[
						23000,
						1,
						0
					],
					[
						23250,
						0,
						0
					],
					[
						23190.625,
						2,
						0
					],
					[
						23443.75,
						2,
						0
					],
					[
						23625,
						2,
						0
					],
					[
						23500,
						0,
						0
					],
					[
						23750,
						3,
						0
					],
					[
						23653.125,
						1,
						0
					],
					[
						23912.5,
						1,
						0
					]
				],
				"lengthInSteps": 16,
				"mustHitSection": true
			},
			{
				"sectionNotes": [
					[
						24000,
						2,
						0
					],
					[
						24250,
						3,
						0
					],
					[
						24500,
						1,
						0
					],
					[
						24375,
						2,
						0
					],
					[
						24534.375,
						3,
						0
					],
					[
						24650,
						2,
						0
					],
					[
						24937.5,
						2,
						0
					],
					[
						24937.5,
						6,
						0
					],
					[
						25175,
						4,
						0
					],
					[
						25175,
						0,
						0
					],
					[
						25250,
						6,
						0
					],
					[
						25250,
						2,
						0
					],
					[
						25500,
						6,
						0
					],
					[
						25500,
						2,
						0
					],
					[
						25421.875,
						4,
						0
					],
					[
						25421.875,
						0,
						0
					],
					[
						25668.75,
						3,
						0
					],
					[
						25668.75,
						7,
						0
					],
					[
						25750,
						0,
						0
					],
					[
						25750,
						4,
						0
					],
					[
						25925,
						1,
						0
					],
					[
						25925,
						5,
						0
					]
				],
				"lengthInSteps": 16,
				"mustHitSection": true
			},
			{
				"sectionNotes": [
					[
						26000,
						3,
						0
					],
					[
						27943.75,
						0,
						0
					],
					[
						27750,
						2,
						0
					],
					[
						26250,
						2,
						0
					],
					[
						26500,
						2,
						0
					],
					[
						26375,
						1,
						0
					],
					[
						26125,
						1,
						0
					],
					[
						26625,
						3,
						0
					],
					[
						26750,
						1,
						0
					],
					[
						26875,
						0,
						0
					],
					[
						27000,
						1,
						0
					],
					[
						27250,
						1,
						0
					],
					[
						27500,
						1,
						0
					],
					[
						27375,
						2,
						0
					],
					[
						27196.875,
						2,
						0
					],
					[
						27125,
						3,
						0
					],
					[
						27625,
						0,
						0
					]
				],
				"lengthInSteps": 16,
				"mustHitSection": false
			},
			{
				"sectionNotes": [
					[
						28000,
						1,
						0
					],
					[
						28250,
						1,
						0
					],
					[
						28500,
						1,
						0
					],
					[
						28750,
						1,
						0
					],
					[
						29000,
						1,
						0
					],
					[
						28875,
						0,
						0
					],
					[
						28625,
						2,
						0
					],
					[
						28375,
						0,
						0
					],
					[
						28125,
						2,
						0
					],
					[
						29125,
						3,
						0
					],
					[
						29212.5,
						2,
						0
					],
					[
						29296.875,
						3,
						0
					],
					[
						29375,
						1,
						0
					],
					[
						29428.125,
						0,
						0
					],
					[
						29500,
						2,
						0
					],
					[
						29715.625,
						1,
						0
					],
					[
						29625,
						1,
						0
					],
					[
						29900,
						3,
						0
					]
				],
				"lengthInSteps": 16,
				"mustHitSection": false
			},
			{
				"sectionNotes": [
					[
						30000,
						3,
						0
					],
					[
						31943.75,
						0,
						0
					],
					[
						31750,
						2,
						0
					],
					[
						30250,
						2,
						0
					],
					[
						30500,
						2,
						0
					],
					[
						30375,
						1,
						0
					],
					[
						30125,
						1,
						0
					],
					[
						30625,
						3,
						0
					],
					[
						30750,
						1,
						0
					],
					[
						30875,
						0,
						0
					],
					[
						31000,
						1,
						0
					],
					[
						31250,
						1,
						0
					],
					[
						31500,
						1,
						0
					],
					[
						31375,
						2,
						0
					],
					[
						31196.875,
						2,
						0
					],
					[
						31125,
						3,
						0
					],
					[
						31625,
						0,
						0
					]
				],
				"lengthInSteps": 16,
				"mustHitSection": true
			},
			{
				"sectionNotes": [
					[
						32000,
						1,
						0
					],
					[
						32250,
						1,
						0
					],
					[
						32500,
						1,
						0
					],
					[
						32750,
						1,
						0
					],
					[
						33000,
						1,
						0
					],
					[
						32875,
						0,
						0
					],
					[
						32625,
						2,
						0
					],
					[
						32375,
						0,
						0
					],
					[
						32125,
						2,
						0
					],
					[
						33125,
						3,
						0
					],
					[
						33212.5,
						2,
						0
					],
					[
						33296.875,
						3,
						0
					],
					[
						33375,
						1,
						0
					],
					[
						33428.125,
						0,
						0
					],
					[
						33500,
						2,
						0
					],
					[
						33715.625,
						1,
						0
					],
					[
						33625,
						1,
						0
					],
					[
						33900,
						3,
						0
					]
				],
				"lengthInSteps": 16,
				"mustHitSection": true
			},
			{
				"sectionNotes": [
					[
						34000,
						3,
						0
					],
					[
						34500,
						3,
						0
					],
					[
						34750,
						1,
						0
					],
					[
						35000,
						2,
						0
					],
					[
						35250,
						0,
						0
					],
					[
						35375,
						2,
						0
					],
					[
						35625,
						1,
						0
					],
					[
						35837.5,
						0,
						0
					],
					[
						35875,
						3,
						250
					]
				],
				"lengthInSteps": 16,
				"mustHitSection": false
			},
			{
				"sectionNotes": [
					[
						36250,
						1,
						0
					],
					[
						36500,
						3,
						0
					],
					[
						36750,
						1,
						0
					],
					[
						37000,
						0,
						0
					],
					[
						37375,
						0,
						0
					],
					[
						37250,
						3,
						0
					],
					[
						37625,
						1,
						0
					],
					[
						37875,
						1,
						0
					]
				],
				"lengthInSteps": 16,
				"mustHitSection": true
			},
			{
				"sectionNotes": [
					[
						38250,
						1,
						0,
						"Mom Sing"
					],
					[
						38500,
						3,
						0,
						"Mom Sing"
					],
					[
						38750,
						1,
						0,
						"Mom Sing"
					],
					[
						39000,
						2,
						0,
						"Mom Sing"
					],
					[
						39125,
						3,
						0,
						"Mom Sing"
					],
					[
						39375,
						1,
						0,
						"Mom Sing"
					],
					[
						39625,
						0,
						0,
						"Mom Sing"
					],
					[
						39875,
						1,
						0,
						"Mom Sing"
					]
				],
				"lengthInSteps": 16,
				"mustHitSection": false
			},
			{
				"sectionNotes": [
					[
						40250,
						1,
						0
					],
					[
						40500,
						0,
						0
					],
					[
						40625,
						1,
						0
					],
					[
						40875,
						3,
						0
					],
					[
						41125,
						1,
						0
					],
					[
						41250,
						3,
						0
					],
					[
						41375,
						1,
						0
					],
					[
						41500,
						3,
						0
					],
					[
						41625,
						2,
						0
					],
					[
						41750,
						1,
						0
					],
					[
						41875,
						3,
						0
					]
				],
				"lengthInSteps": 16,
				"mustHitSection": true
			},
			{
				"sectionNotes": [
					[
						42000,
						3,
						0
					],
					[
						42125,
						2,
						0
					],
					[
						42250,
						1,
						0
					],
					[
						42375,
						0,
						0
					],
					[
						42500,
						3,
						0
					],
					[
						42625,
						0,
						0
					],
					[
						42750,
						3,
						0
					],
					[
						43000,
						1,
						0
					],
					[
						43184.375,
						1,
						0
					],
					[
						43081.25,
						0,
						0
					],
					[
						42846.875,
						0,
						0
					],
					[
						43750,
						0,
						0
					],
					[
						43875,
						3,
						0
					],
					[
						43625,
						1,
						0
					],
					[
						43250,
						3,
						0
					],
					[
						43440.625,
						1,
						0
					]
				],
				"lengthInSteps": 16,
				"mustHitSection": false
			},
			{
				"sectionNotes": [
					[
						44125,
						2,
						0
					],
					[
						44250,
						1,
						0
					],
					[
						44375,
						0,
						0
					],
					[
						44500,
						3,
						0
					],
					[
						44625,
						0,
						0
					],
					[
						44750,
						3,
						0
					],
					[
						45000,
						1,
						0
					],
					[
						45184.375,
						1,
						0
					],
					[
						45081.25,
						0,
						0
					],
					[
						44846.875,
						0,
						0
					],
					[
						45250,
						3,
						0
					],
					[
						45440.625,
						1,
						0
					],
					[
						45625,
						0,
						0
					],
					[
						45875,
						1,
						0
					],
					[
						45750,
						3,
						0
					]
				],
				"lengthInSteps": 16,
				"mustHitSection": true
			},
			{
				"sectionNotes": [
					[
						46125,
						3,
						0,
						"Mom Sing"
					],
					[
						46250,
						1,
						0,
						"Mom Sing"
					],
					[
						46375,
						2,
						0,
						"Mom Sing"
					],
					[
						46500,
						3,
						0,
						"Mom Sing"
					],
					[
						46625,
						1,
						0,
						"Mom Sing"
					],
					[
						46750,
						2,
						0,
						"Mom Sing"
					],
					[
						46875,
						3,
						0,
						"Mom Sing"
					],
					[
						47125,
						3,
						0,
						"Mom Sing"
					],
					[
						47000,
						0,
						0,
						"Mom Sing"
					],
					[
						47250,
						0,
						0,
						"Mom Sing"
					],
					[
						47375,
						1,
						0,
						"Mom Sing"
					],
					[
						47625,
						3,
						0,
						"Mom Sing"
					],
					[
						47750,
						1,
						0,
						"Mom Sing"
					],
					[
						47875,
						2,
						0,
						"Mom Sing"
					]
				],
				"lengthInSteps": 16,
				"mustHitSection": false
			},
			{
				"sectionNotes": [
					[
						48125,
						1,
						0
					],
					[
						48250,
						0,
						0
					],
					[
						48300,
						3,
						0
					],
					[
						48500,
						1,
						0
					],
					[
						48381.25,
						2,
						0
					],
					[
						48625,
						0,
						0
					],
					[
						48750,
						1,
						0
					],
					[
						48875,
						3,
						0
					],
					[
						49125,
						1,
						0
					],
					[
						49250,
						3,
						0
					],
					[
						49500,
						3,
						0
					],
					[
						49750,
						3,
						0
					],
					[
						49375,
						1,
						0
					],
					[
						49625,
						0,
						0
					],
					[
						49875,
						1,
						0
					]
				],
				"lengthInSteps": 16,
				"mustHitSection": true
			},
			{
				"sectionNotes": [
					[
						50000,
						0,
						750
					]
				],
				"lengthInSteps": 16,
				"mustHitSection": true
			},
			{
				"sectionNotes": [
					[
						52125,
						0,
						0,
						"Duo Note"
					],
					[
						52250,
						2,
						0,
						"Duo Note"
					],
					[
						52500,
						3,
						0,
						"Duo Note"
					],
					[
						52375,
						0,
						0,
						"Duo Note"
					],
					[
						52312.5,
						3,
						0,
						"Duo Note"
					],
					[
						52625,
						0,
						0,
						"Duo Note"
					],
					[
						52875,
						1,
						0,
						"Duo Note"
					],
					[
						53062.5,
						0,
						0,
						"Duo Note"
					],
					[
						53125,
						1,
						0,
						"Duo Note"
					],
					[
						53375,
						0,
						0,
						"Duo Note"
					],
					[
						53500,
						3,
						0,
						"Duo Note"
					],
					[
						53562.5,
						2,
						0,
						"Duo Note"
					],
					[
						53750,
						0,
						0,
						"Duo Note"
					]
				],
				"lengthInSteps": 16,
				"mustHitSection": false
			},
			{
				"sectionNotes": [
					[
						54125,
						0,
						0
					],
					[
						54375,
						0,
						0
					],
					[
						54625,
						0,
						0
					],
					[
						54250,
						2,
						0
					],
					[
						54331.25,
						3,
						0
					],
					[
						54543.75,
						3,
						0
					],
					[
						54875,
						1,
						0
					],
					[
						55250,
						2,
						0
					],
					[
						55315.625,
						3,
						0
					],
					[
						55068.75,
						0,
						0
					],
					[
						55375,
						1,
						0
					],
					[
						55500,
						0,
						0
					],
					[
						55553.125,
						2,
						0
					],
					[
						55796.875,
						1,
						0
					]
				],
				"lengthInSteps": 16,
				"mustHitSection": true
			},
			{
				"sectionNotes": [
					[
						57375,
						3,
						0,
						"Mom Sing"
					],
					[
						57375,
						3,
						0
					],
					[
						57750,
						0,
						0,
						"Duo Note"
					],
					[
						57500,
						1,
						0,
						"Duo Note"
					],
					[
						57250,
						1,
						0,
						"Duo Note"
					],
					[
						57125,
						0,
						0,
						"Duo Note"
					],
					[
						56000,
						0,
						0,
						"Duo Note"
					],
					[
						56125,
						2,
						0,
						"Duo Note"
					],
					[
						56250,
						2,
						0,
						"Duo Note"
					],
					[
						56312.5,
						1,
						0,
						"Duo Note"
					],
					[
						56375,
						0,
						0,
						"Duo Note"
					],
					[
						56500,
						3,
						0,
						"Duo Note"
					],
					[
						56687.5,
						2,
						0,
						"Duo Note"
					],
					[
						56750,
						3,
						0,
						"Duo Note"
					],
					[
						56875,
						0,
						0,
						"Duo Note"
					],
					[
						57000,
						2,
						0,
						"Duo Note"
					]
				],
				"lengthInSteps": 16,
				"mustHitSection": false
			},
			{
				"sectionNotes": [
					[
						58000,
						0,
						0
					],
					[
						58125,
						2,
						0
					],
					[
						58250,
						2,
						0
					],
					[
						58300,
						1,
						0
					],
					[
						58375,
						0,
						0
					],
					[
						58500,
						3,
						0
					],
					[
						58750,
						3,
						0
					],
					[
						58678.125,
						2,
						0
					],
					[
						59000,
						2,
						0
					],
					[
						58875,
						0,
						0
					],
					[
						59125,
						0,
						0
					],
					[
						59250,
						1,
						0
					],
					[
						59375,
						3,
						0
					],
					[
						59500,
						0,
						0
					],
					[
						59537.5,
						2,
						0
					],
					[
						59750,
						1,
						0
					]
				],
				"lengthInSteps": 16,
				"mustHitSection": true
			},
			{
				"sectionNotes": [
					[
						60125,
						0,
						0,
						"Duo Note"
					],
					[
						60250,
						2,
						0,
						"Duo Note"
					],
					[
						60312.5,
						1,
						0,
						"Duo Note"
					],
					[
						60375,
						0,
						0,
						"Duo Note"
					],
					[
						60500,
						1,
						0,
						"Duo Note"
					],
					[
						60625,
						0,
						0,
						"Duo Note"
					],
					[
						60750,
						1,
						0,
						"Duo Note"
					],
					[
						60875,
						0,
						0,
						"Duo Note"
					],
					[
						61000,
						2,
						0,
						"Duo Note"
					],
					[
						61125,
						1,
						0,
						"Duo Note"
					],
					[
						61250,
						2,
						0,
						"Duo Note"
					],
					[
						61375,
						0,
						0,
						"Duo Note"
					],
					[
						61500,
						1,
						0,
						"Duo Note"
					],
					[
						61562.5,
						2,
						0,
						"Duo Note"
					],
					[
						61750,
						1,
						0,
						"Duo Note"
					]
				],
				"lengthInSteps": 16,
				"mustHitSection": false
			},
			{
				"sectionNotes": [
					[
						62000,
						2,
						0
					],
					[
						62250,
						3,
						0
					],
					[
						62178.125,
						1,
						0
					],
					[
						62415.625,
						2,
						0
					],
					[
						62500,
						1,
						0
					],
					[
						62750,
						0,
						0
					],
					[
						62646.875,
						3,
						0
					],
					[
						62875,
						3,
						0
					],
					[
						63000,
						0,
						0
					],
					[
						63159.375,
						1,
						0
					],
					[
						63250,
						3,
						0
					],
					[
						63437.5,
						1,
						0
					],
					[
						63500,
						3,
						0
					],
					[
						63750,
						1,
						0
					],
					[
						63581.25,
						2,
						0
					]
				],
				"lengthInSteps": 16,
				"mustHitSection": true
			},
			{
				"sectionNotes": [
					[
						64000,
						3,
						0,
						"Duo Note"
					],
					[
						64125,
						0,
						0,
						"Duo Note"
					],
					[
						64375,
						0,
						0,
						"Duo Note"
					],
					[
						64500,
						2,
						0,
						"Duo Note"
					],
					[
						64625,
						3,
						0,
						"Duo Note"
					],
					[
						64750,
						0,
						0,
						"Duo Note"
					],
					[
						64875,
						2,
						0,
						"Duo Note"
					],
					[
						65000,
						3,
						0,
						"Duo Note"
					],
					[
						65125,
						0,
						0,
						"Duo Note"
					],
					[
						65250,
						3,
						0,
						"Duo Note"
					],
					[
						65375,
						1,
						0,
						"Duo Note"
					],
					[
						65500,
						3,
						0,
						"Duo Note"
					],
					[
						65625,
						0,
						0,
						"Duo Note"
					],
					[
						65875,
						2,
						0,
						"Duo Note"
					],
					[
						65750,
						1,
						0,
						"Duo Note"
					]
				],
				"lengthInSteps": 16,
				"mustHitSection": false
			},
			{
				"sectionNotes": [
					[
						66000,
						0,
						0
					],
					[
						66125,
						2,
						0
					],
					[
						66375,
						2,
						0
					],
					[
						66500,
						3,
						0
					],
					[
						66750,
						3,
						0
					],
					[
						66625,
						1,
						0
					],
					[
						66875,
						1,
						0
					],
					[
						67000,
						0,
						0
					],
					[
						67250,
						0,
						0
					],
					[
						67750,
						2,
						0
					],
					[
						67500,
						1,
						0
					]
				],
				"lengthInSteps": 16,
				"mustHitSection": true
			},
			{
				"sectionNotes": [
					[
						68500,
						3,
						0
					],
					[
						68750,
						3,
						0
					],
					[
						68578.125,
						0,
						0
					],
					[
						68668.75,
						1,
						0
					],
					[
						68940.625,
						2,
						0
					],
					[
						69125,
						3,
						0
					],
					[
						69375,
						3,
						0
					],
					[
						69250,
						1,
						0
					],
					[
						69500,
						1,
						0
					],
					[
						69625,
						0,
						0
					],
					[
						69750,
						1,
						0
					],
					[
						69875,
						0,
						0
					],
					[
						68000,
						4,
						875
					]
				],
				"lengthInSteps": 16,
				"mustHitSection": false
			},
			{
				"sectionNotes": [
					[
						70000,
						3,
						0
					],
					[
						70250,
						1,
						0
					],
					[
						70693.75,
						1,
						0
					],
					[
						70750,
						2,
						0
					],
					[
						70625,
						0,
						0
					],
					[
						70946.875,
						3,
						0
					],
					[
						71750,
						3,
						0
					],
					[
						71500,
						3,
						0
					],
					[
						71375,
						1,
						0
					],
					[
						71125,
						3,
						0
					],
					[
						71625,
						0,
						0
					],
					[
						71909.375,
						1,
						0
					]
				],
				"lengthInSteps": 16,
				"mustHitSection": false
			},
			{
				"sectionNotes": [
					[
						72000,
						7,
						0
					],
					[
						72250,
						5,
						0
					],
					[
						72500,
						3,
						0
					],
					[
						72750,
						3,
						0
					],
					[
						72578.125,
						0,
						0
					],
					[
						72668.75,
						1,
						0
					],
					[
						72940.625,
						2,
						0
					],
					[
						73125,
						3,
						0
					],
					[
						73375,
						3,
						0
					],
					[
						73250,
						1,
						0
					],
					[
						73500,
						1,
						0
					],
					[
						73625,
						0,
						0
					],
					[
						73750,
						1,
						0
					],
					[
						73875,
						0,
						0
					]
				],
				"lengthInSteps": 16,
				"mustHitSection": true
			},
			{
				"sectionNotes": [
					[
						74000,
						3,
						0
					],
					[
						74250,
						1,
						0
					],
					[
						74693.75,
						1,
						0
					],
					[
						74750,
						2,
						0
					],
					[
						74625,
						0,
						0
					],
					[
						74946.875,
						3,
						0
					],
					[
						75500,
						3,
						0
					],
					[
						75375,
						1,
						0
					],
					[
						75125,
						3,
						0
					],
					[
						75909.375,
						1,
						0
					],
					[
						75625,
						1,
						0
					],
					[
						75750,
						0,
						0
					]
				],
				"lengthInSteps": 16,
				"mustHitSection": true
			},
			{
				"sectionNotes": [
					[
						76000,
						0,
						375
					],
					[
						76500,
						2,
						250
					],
					[
						76875,
						3,
						0
					],
					[
						77000,
						0,
						0
					],
					[
						76928.125,
						1,
						0
					],
					[
						77250,
						1,
						0
					],
					[
						77500,
						2,
						0
					],
					[
						77678.125,
						1,
						0
					],
					[
						77921.875,
						0,
						0
					]
				],
				"lengthInSteps": 16,
				"mustHitSection": false
			},
			{
				"sectionNotes": [
					[
						78125,
						3,
						0
					],
					[
						78250,
						0,
						0
					],
					[
						78375,
						1,
						0
					],
					[
						78500,
						0,
						0
					],
					[
						78625,
						1,
						0
					],
					[
						78750,
						3,
						0
					],
					[
						78875,
						0,
						0
					],
					[
						78940.625,
						1,
						0
					],
					[
						79125,
						0,
						0
					],
					[
						79250,
						3,
						0
					],
					[
						79500,
						3,
						0
					],
					[
						79375,
						1,
						0
					],
					[
						79625,
						0,
						0
					],
					[
						79750,
						1,
						0
					],
					[
						79928.125,
						2,
						0
					]
				],
				"lengthInSteps": 16,
				"mustHitSection": false
			},
			{
				"sectionNotes": [
					[
						80000,
						0,
						375
					],
					[
						81000,
						0,
						0
					],
					[
						81250,
						1,
						0
					],
					[
						81500,
						2,
						0
					],
					[
						81678.125,
						1,
						0
					],
					[
						81921.875,
						0,
						0
					],
					[
						80500,
						1,
						0
					],
					[
						80875,
						1,
						0
					],
					[
						80940.625,
						3,
						0
					]
				],
				"lengthInSteps": 16,
				"mustHitSection": true
			},
			{
				"sectionNotes": [
					[
						82125,
						3,
						0
					],
					[
						82250,
						0,
						0
					],
					[
						82375,
						1,
						0
					],
					[
						82500,
						0,
						0
					],
					[
						82625,
						1,
						0
					],
					[
						82750,
						3,
						0
					],
					[
						82875,
						0,
						0
					],
					[
						82940.625,
						1,
						0
					],
					[
						83125,
						0,
						0
					],
					[
						83250,
						3,
						0
					],
					[
						83375,
						1,
						0
					]
				],
				"lengthInSteps": 16,
				"mustHitSection": true
			},
			{
				"sectionNotes": [
					[
						84206.25,
						3,
						0,
						"Mom Sing"
					],
					[
						84081.25,
						1,
						0,
						"Mom Sing"
					],
					[
						84428.125,
						1,
						0,
						"Mom Sing"
					],
					[
						84596.875,
						1,
						0,
						"Mom Sing"
					],
					[
						84906.25,
						1,
						0,
						"Mom Sing"
					],
					[
						85171.875,
						3,
						0,
						"Mom Sing"
					],
					[
						85665.625,
						1,
						0,
						"Mom Sing"
					],
					[
						85912.5,
						3,
						0,
						"Mom Sing"
					],
					[
						84000,
						2,
						0,
						"Mom Sing"
					],
					[
						84250,
						0,
						0,
						"Mom Sing"
					],
					[
						84500,
						2,
						0,
						"Mom Sing"
					],
					[
						84687.5,
						3,
						0,
						"Mom Sing"
					],
					[
						84750,
						0,
						0,
						"Mom Sing"
					],
					[
						85000,
						2,
						0,
						"Mom Sing"
					],
					[
						85250,
						2,
						0,
						"Mom Sing"
					],
					[
						85500,
						2,
						0,
						"Mom Sing"
					],
					[
						85437.5,
						1,
						0,
						"Mom Sing"
					],
					[
						85750,
						2,
						0,
						"Mom Sing"
					]
				],
				"lengthInSteps": 16,
				"mustHitSection": false
			},
			{
				"sectionNotes": [
					[
						86000,
						0,
						0
					],
					[
						86081.25,
						3,
						0
					],
					[
						86190.625,
						2,
						0
					],
					[
						86250,
						1,
						0
					],
					[
						86406.25,
						2,
						0
					],
					[
						86500,
						1,
						0
					],
					[
						86665.625,
						3,
						0
					],
					[
						86750,
						2,
						0
					],
					[
						86900,
						3,
						0
					],
					[
						87000,
						2,
						0
					],
					[
						87125,
						0,
						0
					],
					[
						87250,
						2,
						0
					],
					[
						87375,
						3,
						0
					],
					[
						87500,
						2,
						0
					],
					[
						87625,
						3,
						0
					],
					[
						87750,
						1,
						0
					],
					[
						87875,
						3,
						0
					]
				],
				"lengthInSteps": 16,
				"mustHitSection": true
			},
			{
				"sectionNotes": [
					[
						88206.25,
						3,
						0,
						"Mom Sing"
					],
					[
						88081.25,
						1,
						0,
						"Mom Sing"
					],
					[
						88428.125,
						1,
						0,
						"Mom Sing"
					],
					[
						88596.875,
						1,
						0,
						"Mom Sing"
					],
					[
						88906.25,
						1,
						0,
						"Mom Sing"
					],
					[
						89171.875,
						3,
						0,
						"Mom Sing"
					],
					[
						88000,
						2,
						0,
						"Mom Sing"
					],
					[
						88250,
						0,
						0,
						"Mom Sing"
					],
					[
						88500,
						2,
						0,
						"Mom Sing"
					],
					[
						88687.5,
						3,
						0,
						"Mom Sing"
					],
					[
						88750,
						0,
						0,
						"Mom Sing"
					],
					[
						89000,
						2,
						0,
						"Mom Sing"
					],
					[
						89375,
						1,
						0,
						"Mom Sing"
					],
					[
						89625,
						1,
						0,
						"Mom Sing"
					],
					[
						89500,
						3,
						0,
						"Mom Sing"
					],
					[
						89750,
						3,
						0,
						"Mom Sing"
					],
					[
						89875,
						1,
						0,
						"Mom Sing"
					],
					[
						89250,
						2,
						0,
						"Mom Sing"
					]
				],
				"lengthInSteps": 16,
				"mustHitSection": false
			},
			{
				"sectionNotes": [
					[
						90000,
						0,
						0
					],
					[
						90125,
						1,
						0
					],
					[
						90250,
						2,
						0
					],
					[
						90375,
						1,
						0
					],
					[
						90500,
						0,
						0
					],
					[
						90625,
						1,
						0
					],
					[
						90750,
						2,
						0
					],
					[
						90875,
						1,
						0
					],
					[
						91000,
						0,
						0
					],
					[
						91071.875,
						3,
						0
					],
					[
						91156.25,
						0,
						0
					],
					[
						91250,
						1,
						0
					],
					[
						91375,
						0,
						0
					],
					[
						91500,
						1,
						0
					],
					[
						91625,
						2,
						0
					],
					[
						91750,
						0,
						0
					],
					[
						91875,
						3,
						0
					]
				],
				"lengthInSteps": 16,
				"mustHitSection": true
			},
			{
				"sectionNotes": [
					[
						92206.25,
						3,
						0,
						"Mom Sing"
					],
					[
						92081.25,
						1,
						0,
						"Mom Sing"
					],
					[
						92428.125,
						1,
						0,
						"Mom Sing"
					],
					[
						92596.875,
						1,
						0,
						"Mom Sing"
					],
					[
						92687.5,
						3,
						0,
						"Mom Sing"
					],
					[
						92906.25,
						1,
						0,
						"Mom Sing"
					],
					[
						93912.5,
						3,
						0,
						"Mom Sing"
					],
					[
						93062.5,
						1,
						0,
						"Mom Sing"
					],
					[
						93234.375,
						1,
						0,
						"Mom Sing"
					],
					[
						93406.25,
						1,
						0,
						"Mom Sing"
					],
					[
						93309.375,
						3,
						0,
						"Mom Sing"
					],
					[
						93693.75,
						3,
						0,
						"Mom Sing"
					],
					[
						93587.5,
						0,
						0,
						"Mom Sing"
					],
					[
						93818.75,
						2,
						0,
						"Mom Sing"
					],
					[
						92000,
						2,
						0,
						"Mom Sing"
					],
					[
						92250,
						0,
						0,
						"Mom Sing"
					],
					[
						92500,
						2,
						0,
						"Mom Sing"
					],
					[
						92750,
						0,
						0,
						"Mom Sing"
					],
					[
						93000,
						2,
						0,
						"Mom Sing"
					],
					[
						93125,
						2,
						0,
						"Mom Sing"
					],
					[
						93750,
						1,
						0,
						"Mom Sing"
					],
					[
						93500,
						3,
						0,
						"Mom Sing"
					]
				],
				"lengthInSteps": 16,
				"mustHitSection": false
			},
			{
				"sectionNotes": [
					[
						94000,
						0,
						0
					],
					[
						94125,
						2,
						0
					],
					[
						94190.625,
						1,
						0
					],
					[
						94250,
						0,
						0
					],
					[
						94421.875,
						2,
						0
					],
					[
						94575,
						2,
						0
					],
					[
						94500,
						0,
						0
					],
					[
						94625,
						1,
						0
					],
					[
						94750,
						0,
						0
					],
					[
						94875,
						1,
						0
					],
					[
						95000,
						3,
						0
					],
					[
						95071.875,
						0,
						0
					],
					[
						95328.125,
						3,
						0
					],
					[
						95162.5,
						3,
						0
					],
					[
						95250,
						0,
						0
					],
					[
						95409.375,
						0,
						0
					],
					[
						95500,
						2,
						0
					],
					[
						95875,
						2,
						0
					],
					[
						95681.25,
						2,
						0
					],
					[
						95625,
						3,
						0
					],
					[
						95750,
						1,
						0
					],
					[
						95940.625,
						1,
						0
					]
				],
				"lengthInSteps": 16,
				"mustHitSection": true
			},
			{
				"sectionNotes": [
					[
						96062.5,
						1,
						0,
						"Mom Sing"
					],
					[
						96393.75,
						1,
						0,
						"Mom Sing"
					],
					[
						96556.25,
						1,
						0,
						"Mom Sing"
					],
					[
						97059.375,
						3,
						0,
						"Mom Sing"
					],
					[
						96912.5,
						3,
						0,
						"Mom Sing"
					],
					[
						97215.625,
						3,
						0,
						"Mom Sing"
					],
					[
						97281.25,
						1,
						0,
						"Mom Sing"
					],
					[
						97437.5,
						1,
						0,
						"Mom Sing"
					],
					[
						97587.5,
						1,
						0,
						"Mom Sing"
					],
					[
						97562.5,
						3,
						0,
						"Mom Sing"
					],
					[
						97709.375,
						3,
						0,
						"Mom Sing"
					],
					[
						97815.625,
						0,
						0,
						"Mom Sing"
					],
					[
						97375,
						2,
						0,
						"Mom Sing"
					],
					[
						97000,
						0,
						0,
						"Mom Sing"
					],
					[
						96750,
						0,
						0,
						"Mom Sing"
					],
					[
						96500,
						2,
						0,
						"Mom Sing"
					],
					[
						96000,
						2,
						0,
						"Mom Sing"
					],
					[
						96250,
						0,
						0,
						"Mom Sing"
					],
					[
						96125,
						3,
						0,
						"Mom Sing"
					],
					[
						96625,
						3,
						0,
						"Mom Sing"
					],
					[
						97125,
						1,
						0,
						"Mom Sing"
					],
					[
						97875,
						3,
						0,
						"Mom Sing"
					]
				],
				"lengthInSteps": 16,
				"mustHitSection": false
			},
			{
				"sectionNotes": [
					[
						98000,
						0,
						0
					],
					[
						98125,
						1,
						0
					],
					[
						98250,
						2,
						0
					],
					[
						98375,
						1,
						0
					],
					[
						98500,
						0,
						0
					],
					[
						98625,
						1,
						0
					],
					[
						98750,
						2,
						0
					],
					[
						98875,
						1,
						0
					],
					[
						99000,
						0,
						375
					],
					[
						99500,
						3,
						0
					],
					[
						99750,
						0,
						0
					]
				],
				"lengthInSteps": 16,
				"mustHitSection": true
			},
			{
				"sectionNotes": [
					[
						100000,
						3,
						0
					],
					[
						100375,
						3,
						0
					],
					[
						100125,
						1,
						0
					],
					[
						100250,
						2,
						0
					],
					[
						100500,
						1,
						0
					],
					[
						100625,
						2,
						0
					],
					[
						100750,
						3,
						0
					],
					[
						100875,
						1,
						0
					],
					[
						101000,
						3,
						0
					],
					[
						101125,
						0,
						0
					],
					[
						101250,
						0,
						0
					],
					[
						101375,
						1,
						0
					],
					[
						101500,
						0,
						0
					],
					[
						101625,
						3,
						0
					],
					[
						101750,
						0,
						0
					],
					[
						101875,
						1,
						0
					]
				],
				"lengthInSteps": 16,
				"mustHitSection": false
			},
			{
				"sectionNotes": [
					[
						103875,
						2,
						0
					],
					[
						103750,
						3,
						0
					],
					[
						103500,
						3,
						0
					],
					[
						103625,
						0,
						0
					],
					[
						103375,
						0,
						0
					],
					[
						103250,
						2,
						0
					],
					[
						103125,
						2,
						0
					],
					[
						103000,
						1,
						0
					],
					[
						102875,
						3,
						0
					],
					[
						102750,
						1,
						0
					],
					[
						102625,
						2,
						0
					],
					[
						102500,
						3,
						0
					],
					[
						102375,
						1,
						0
					],
					[
						102250,
						2,
						0
					],
					[
						102125,
						3,
						0
					],
					[
						102000,
						1,
						0
					]
				],
				"lengthInSteps": 16,
				"mustHitSection": true
			},
			{
				"sectionNotes": [
					[
						104000,
						3,
						0,
						"Mom Sing"
					],
					[
						104125,
						1,
						0,
						"Mom Sing"
					],
					[
						104250,
						2,
						0,
						"Mom Sing"
					],
					[
						104375,
						3,
						0,
						"Mom Sing"
					],
					[
						104500,
						1,
						0,
						"Mom Sing"
					],
					[
						104625,
						2,
						0,
						"Mom Sing"
					],
					[
						104750,
						3,
						0,
						"Mom Sing"
					],
					[
						105000,
						3,
						0,
						"Mom Sing"
					],
					[
						104875,
						1,
						0,
						"Mom Sing"
					],
					[
						105125,
						0,
						0,
						"Mom Sing"
					],
					[
						105250,
						0,
						0,
						"Mom Sing"
					],
					[
						105375,
						1,
						0,
						"Mom Sing"
					],
					[
						105500,
						0,
						0,
						"Mom Sing"
					],
					[
						105625,
						3,
						0,
						"Mom Sing"
					],
					[
						105750,
						0,
						0,
						"Mom Sing"
					],
					[
						105875,
						1,
						0,
						"Mom Sing"
					]
				],
				"lengthInSteps": 16,
				"mustHitSection": false
			},
			{
				"sectionNotes": [
					[
						106000,
						2,
						0
					],
					[
						106250,
						3,
						0
					],
					[
						106375,
						2,
						0
					],
					[
						106125,
						0,
						0
					],
					[
						106500,
						0,
						0
					],
					[
						106625,
						3,
						0
					],
					[
						106750,
						2,
						0
					],
					[
						106875,
						0,
						0
					],
					[
						107000,
						2,
						0
					],
					[
						107125,
						3,
						0
					],
					[
						107250,
						3,
						0
					],
					[
						107375,
						2,
						0
					],
					[
						107500,
						0,
						0
					],
					[
						107625,
						2,
						0
					],
					[
						107750,
						1,
						0
					],
					[
						107875,
						2,
						0
					]
				],
				"lengthInSteps": 16,
				"mustHitSection": true
			},
			{
				"sectionNotes": [
					[
						108000,
						3,
						0
					],
					[
						108125,
						1,
						0
					],
					[
						108250,
						2,
						0
					],
					[
						108375,
						3,
						0
					],
					[
						108500,
						1,
						0
					],
					[
						108625,
						2,
						0
					],
					[
						108750,
						3,
						0
					],
					[
						108875,
						1,
						0
					],
					[
						109000,
						7,
						0
					],
					[
						109125,
						5,
						0
					],
					[
						109250,
						6,
						0
					],
					[
						109375,
						7,
						0
					],
					[
						109500,
						5,
						0
					],
					[
						109625,
						6,
						0
					],
					[
						109750,
						7,
						0
					],
					[
						109875,
						5,
						0
					]
				],
				"lengthInSteps": 16,
				"mustHitSection": false
			},
			{
				"sectionNotes": [
					[
						111000,
						7,
						0
					],
					[
						111125,
						5,
						0
					],
					[
						111250,
						6,
						0
					],
					[
						111375,
						7,
						0
					],
					[
						111500,
						5,
						0
					],
					[
						111625,
						6,
						0
					],
					[
						111750,
						7,
						0
					],
					[
						111875,
						5,
						0
					],
					[
						110000,
						3,
						0,
						"Mom Sing"
					],
					[
						110125,
						1,
						0,
						"Mom Sing"
					],
					[
						110250,
						2,
						0,
						"Mom Sing"
					],
					[
						110375,
						3,
						0,
						"Mom Sing"
					],
					[
						110500,
						1,
						0,
						"Mom Sing"
					],
					[
						110625,
						2,
						0,
						"Mom Sing"
					],
					[
						110750,
						3,
						0,
						"Mom Sing"
					],
					[
						110875,
						1,
						0,
						"Mom Sing"
					]
				],
				"lengthInSteps": 16,
				"mustHitSection": false
			},
			{
				"sectionNotes": [
					[
						112000,
						7,
						0
					],
					[
						112125,
						5,
						0
					],
					[
						112250,
						6,
						0
					],
					[
						112375,
						7,
						0
					],
					[
						112500,
						3,
						0
					],
					[
						112625,
						1,
						0
					],
					[
						112750,
						2,
						0
					],
					[
						112875,
						3,
						0
					],
					[
						113500,
						3,
						0
					],
					[
						113625,
						1,
						0
					],
					[
						113750,
						2,
						0
					],
					[
						113875,
						3,
						0
					],
					[
						113000,
						7,
						0,
						"Mom Sing"
					],
					[
						113125,
						5,
						0,
						"Mom Sing"
					],
					[
						113250,
						6,
						0,
						"Mom Sing"
					],
					[
						113375,
						7,
						0,
						"Mom Sing"
					]
				],
				"lengthInSteps": 16,
				"mustHitSection": true
			},
			{
				"sectionNotes": [
					[
						114000,
						0,
						0
					],
					[
						114125,
						1,
						0
					],
					[
						114250,
						0,
						0
					],
					[
						114375,
						1,
						0
					],
					[
						114500,
						0,
						0
					],
					[
						114625,
						1,
						0
					],
					[
						114750,
						0,
						0
					],
					[
						114875,
						1,
						0
					],
					[
						114000,
						4,
						0,
						"Duo Note"
					],
					[
						114125,
						5,
						0,
						"Duo Note"
					],
					[
						114250,
						4,
						0,
						"Duo Note"
					],
					[
						114375,
						5,
						0,
						"Duo Note"
					],
					[
						114500,
						4,
						0,
						"Duo Note"
					],
					[
						114625,
						5,
						0,
						"Duo Note"
					],
					[
						114750,
						4,
						0,
						"Duo Note"
					],
					[
						114875,
						5,
						0,
						"Duo Note"
					]
				],
				"lengthInSteps": 16,
				"mustHitSection": true
			},
			{
				"sectionNotes": [
					[
						116000,
						3,
						0
					],
					[
						116125,
						1,
						0
					],
					[
						116250,
						2,
						0
					],
					[
						116375,
						3,
						0
					],
					[
						116750,
						3,
						0
					],
					[
						116625,
						1,
						0
					],
					[
						116875,
						1,
						0
					],
					[
						117000,
						7,
						0
					],
					[
						117125,
						5,
						0
					],
					[
						117250,
						6,
						0
					],
					[
						117375,
						7,
						0
					],
					[
						117625,
						5,
						0
					],
					[
						117750,
						7,
						0
					],
					[
						117875,
						5,
						0
					]
				],
				"lengthInSteps": 16,
				"mustHitSection": false
			},
			{
				"sectionNotes": [
					[
						118000,
						6,
						0
					],
					[
						118125,
						5,
						0
					],
					[
						118250,
						6,
						0
					],
					[
						118375,
						7,
						0
					],
					[
						118500,
						6,
						0
					],
					[
						118625,
						4,
						0
					],
					[
						118750,
						6,
						0
					],
					[
						118875,
						5,
						0
					],
					[
						119000,
						2,
						0
					],
					[
						119125,
						1,
						0
					],
					[
						119250,
						2,
						0
					],
					[
						119375,
						3,
						0
					],
					[
						119500,
						2,
						0
					],
					[
						119625,
						0,
						0
					],
					[
						119750,
						2,
						0
					],
					[
						119875,
						1,
						0
					]
				],
				"lengthInSteps": 16,
				"mustHitSection": true
			},
			{
				"sectionNotes": [
					[
						120000,
						3,
						0
					],
					[
						120125,
						1,
						0
					],
					[
						120250,
						3,
						0
					],
					[
						120375,
						0,
						0
					],
					[
						120500,
						2,
						0
					],
					[
						120625,
						3,
						0
					],
					[
						120875,
						3,
						0
					],
					[
						120750,
						1,
						0
					],
					[
						120568.75,
						0,
						0
					],
					[
						121000,
						7,
						0
					],
					[
						121250,
						7,
						0
					],
					[
						121125,
						5,
						0
					],
					[
						121375,
						4,
						0
					],
					[
						121575,
						4,
						0
					],
					[
						121500,
						6,
						0
					],
					[
						121625,
						7,
						0
					],
					[
						121750,
						5,
						0
					],
					[
						121875,
						7,
						0
					]
				],
				"lengthInSteps": 16,
				"mustHitSection": false
			},
			{
				"sectionNotes": [
					[
						122000,
						2,
						0
					],
					[
						122125,
						3,
						0
					],
					[
						122250,
						2,
						0
					],
					[
						122375,
						0,
						0
					],
					[
						122500,
						2,
						0
					],
					[
						122625,
						3,
						0
					],
					[
						122750,
						2,
						0
					],
					[
						122875,
						4,
						875
					]
				],
				"lengthInSteps": 16,
				"mustHitSection": false
			},
			{
				"sectionNotes": [
					[
						125000,
						7,
						0
					],
					[
						125125,
						5,
						0
					],
					[
						125250,
						6,
						0
					],
					[
						125375,
						5,
						0
					],
					[
						125500,
						6,
						0
					],
					[
						125625,
						7,
						0
					],
					[
						125750,
						5,
						0
					],
					[
						125875,
						4,
						0
					],
					[
						124000,
						3,
						0,
						"Mom Sing"
					],
					[
						124125,
						1,
						0,
						"Mom Sing"
					],
					[
						124250,
						2,
						0,
						"Mom Sing"
					],
					[
						124375,
						1,
						0,
						"Mom Sing"
					],
					[
						124500,
						2,
						0,
						"Mom Sing"
					],
					[
						124625,
						3,
						0,
						"Mom Sing"
					],
					[
						124750,
						1,
						0,
						"Mom Sing"
					],
					[
						124875,
						0,
						0,
						"Mom Sing"
					]
				],
				"lengthInSteps": 16,
				"mustHitSection": false
			},
			{
				"sectionNotes": [
					[
						127000,
						1,
						0
					],
					[
						127125,
						3,
						0
					],
					[
						127050,
						2,
						0
					],
					[
						127250,
						1,
						0
					],
					[
						127375,
						3,
						0
					],
					[
						127500,
						1,
						0
					],
					[
						127625,
						0,
						0
					],
					[
						127750,
						2,
						0
					],
					[
						127875,
						0,
						0
					],
					[
						126000,
						5,
						0,
						"Mom Sing"
					],
					[
						126062.5,
						6,
						0,
						"Mom Sing"
					],
					[
						126125,
						7,
						0,
						"Mom Sing"
					],
					[
						126250,
						5,
						0,
						"Mom Sing"
					],
					[
						126375,
						7,
						0,
						"Mom Sing"
					],
					[
						126500,
						5,
						0,
						"Mom Sing"
					],
					[
						126625,
						4,
						0,
						"Mom Sing"
					],
					[
						126750,
						6,
						0,
						"Mom Sing"
					],
					[
						126875,
						4,
						0,
						"Mom Sing"
					]
				],
				"lengthInSteps": 16,
				"mustHitSection": true
			},
			{
				"sectionNotes": [
					[
						129000,
						5,
						0
					],
					[
						129125,
						6,
						0
					],
					[
						129250,
						5,
						0
					],
					[
						129375,
						4,
						0
					],
					[
						129500,
						5,
						0
					],
					[
						129625,
						6,
						0
					],
					[
						129750,
						5,
						0
					],
					[
						129875,
						4,
						0
					],
					[
						128125,
						2,
						0,
						"Mom Sing"
					],
					[
						128000,
						1,
						0,
						"Mom Sing"
					],
					[
						128250,
						1,
						0,
						"Mom Sing"
					],
					[
						128375,
						0,
						0,
						"Mom Sing"
					],
					[
						128500,
						1,
						0,
						"Mom Sing"
					],
					[
						128625,
						2,
						0,
						"Mom Sing"
					],
					[
						128750,
						1,
						0,
						"Mom Sing"
					],
					[
						128875,
						0,
						0,
						"Mom Sing"
					]
				],
				"lengthInSteps": 16,
				"mustHitSection": false
			},
			{
				"lengthInSteps": 16,
				"typeOfSection": 0,
				"sectionNotes": [
					[
						131000,
						1,
						0
					],
					[
						131187.5,
						0,
						0
					],
					[
						131250,
						3,
						0
					],
					[
						131062.5,
						3,
						0
					],
					[
						131875,
						3,
						0
					],
					[
						131750,
						1,
						0
					],
					[
						131462.5,
						0,
						0
					],
					[
						131325,
						1,
						0
					],
					[
						131500,
						2,
						0
					],
					[
						131681.25,
						1,
						0
					],
					[
						130875,
						7,
						0,
						"Mom Sing"
					],
					[
						130500,
						6,
						0,
						"Mom Sing"
					],
					[
						130000,
						5,
						0,
						"Mom Sing"
					],
					[
						130250,
						7,
						0,
						"Mom Sing"
					],
					[
						130062.5,
						7,
						0,
						"Mom Sing"
					],
					[
						130187.5,
						4,
						0,
						"Mom Sing"
					],
					[
						130312.5,
						5,
						0,
						"Mom Sing"
					],
					[
						130437.5,
						4,
						0,
						"Mom Sing"
					]
				],
				"altAnim": false,
				"bpm": 180,
				"changeBPM": false,
				"mustHitSection": true
			},
			{
				"lengthInSteps": 16,
				"typeOfSection": 0,
				"sectionNotes": [
					[
						132000,
						3,
						0
					],
					[
						132125,
						0,
						0
					],
					[
						132071.875,
						1,
						0
					],
					[
						132250,
						2,
						0
					],
					[
						132375,
						3,
						0
					],
					[
						132500,
						1,
						0
					],
					[
						132625,
						0,
						0
					],
					[
						132750,
						0,
						0
					],
					[
						132706.25,
						2,
						0
					],
					[
						132943.75,
						2,
						0
					],
					[
						133000,
						3,
						0
					],
					[
						133750,
						0,
						0
					],
					[
						133500,
						0,
						0
					],
					[
						133250,
						0,
						0
					],
					[
						133375,
						2,
						0
					],
					[
						133125,
						2,
						0
					],
					[
						133625,
						1,
						0
					],
					[
						133875,
						1,
						0
					]
				],
				"altAnim": false,
				"bpm": 150,
				"changeBPM": false,
				"mustHitSection": false
			},
			{
				"lengthInSteps": 16,
				"typeOfSection": 0,
				"sectionNotes": [
					[
						134000,
						1,
						0
					],
					[
						134250,
						1,
						0
					],
					[
						134193.75,
						0,
						0
					],
					[
						134071.875,
						3,
						0
					],
					[
						134375,
						1,
						0
					],
					[
						134500,
						3,
						0
					],
					[
						134625,
						0,
						0
					],
					[
						134671.875,
						1,
						0
					],
					[
						134750,
						0,
						0
					],
					[
						134912.5,
						3,
						0
					],
					[
						135000,
						1,
						0
					],
					[
						135250,
						3,
						0
					],
					[
						135156.25,
						0,
						0
					],
					[
						135500,
						3,
						0
					],
					[
						135440.625,
						1,
						0
					],
					[
						135750,
						2,
						0
					]
				],
				"altAnim": false,
				"bpm": 150,
				"changeBPM": false,
				"mustHitSection": true
			},
			{
				"lengthInSteps": 16,
				"typeOfSection": 0,
				"sectionNotes": [
					[
						136071.875,
						1,
						0,
						"Mom Sing"
					],
					[
						136706.25,
						2,
						0,
						"Mom Sing"
					],
					[
						136943.75,
						2,
						0,
						"Mom Sing"
					],
					[
						137750,
						0,
						0,
						"Mom Sing"
					],
					[
						137500,
						0,
						0,
						"Mom Sing"
					],
					[
						137250,
						0,
						0,
						"Mom Sing"
					],
					[
						137125,
						2,
						0,
						"Mom Sing"
					],
					[
						137000,
						3,
						0,
						"Mom Sing"
					],
					[
						137375,
						2,
						0,
						"Mom Sing"
					],
					[
						137625,
						1,
						0,
						"Mom Sing"
					],
					[
						137875,
						1,
						0,
						"Mom Sing"
					],
					[
						136625,
						0,
						0,
						"Mom Sing"
					],
					[
						136750,
						0,
						0,
						"Mom Sing"
					],
					[
						136500,
						1,
						0,
						"Mom Sing"
					],
					[
						136375,
						3,
						0,
						"Mom Sing"
					],
					[
						136250,
						2,
						0,
						"Mom Sing"
					],
					[
						136125,
						0,
						0,
						"Mom Sing"
					],
					[
						136000,
						3,
						0,
						"Mom Sing"
					]
				],
				"altAnim": false,
				"bpm": 150,
				"changeBPM": false,
				"mustHitSection": false
			},
			{
				"lengthInSteps": 16,
				"typeOfSection": 0,
				"sectionNotes": [
					[
						138000,
						0,
						0
					],
					[
						138125,
						1,
						0
					],
					[
						138200,
						3,
						0
					],
					[
						138250,
						1,
						0
					],
					[
						138375,
						0,
						0
					],
					[
						138500,
						1,
						0
					],
					[
						138625,
						1,
						0
					],
					[
						138571.875,
						3,
						0
					],
					[
						138750,
						0,
						0
					],
					[
						139000,
						0,
						0
					],
					[
						138875,
						3,
						0
					],
					[
						139250,
						3,
						0
					],
					[
						139500,
						1,
						0
					],
					[
						139750,
						2,
						0
					]
				],
				"altAnim": false,
				"bpm": 150,
				"changeBPM": false,
				"mustHitSection": true
			},
			{
				"lengthInSteps": 16,
				"typeOfSection": 0,
				"sectionNotes": [
					[
						140000,
						3,
						0
					],
					[
						140125,
						0,
						0
					],
					[
						140071.875,
						1,
						0
					],
					[
						140250,
						2,
						0
					],
					[
						140375,
						3,
						0
					],
					[
						140500,
						1,
						0
					],
					[
						140625,
						0,
						0
					],
					[
						140750,
						0,
						0
					],
					[
						140706.25,
						2,
						0
					],
					[
						140943.75,
						2,
						0
					],
					[
						141000,
						3,
						0
					],
					[
						141500,
						0,
						0
					],
					[
						141250,
						0,
						0
					],
					[
						141375,
						2,
						0
					],
					[
						141125,
						2,
						0
					],
					[
						141575,
						1,
						0
					],
					[
						141696.875,
						0,
						0
					],
					[
						141750,
						1,
						0
					],
					[
						141934.375,
						0,
						0
					]
				],
				"altAnim": false,
				"bpm": 150,
				"changeBPM": false,
				"mustHitSection": false
			},
			{
				"lengthInSteps": 16,
				"typeOfSection": 0,
				"sectionNotes": [
					[
						142000,
						1,
						0
					],
					[
						142250,
						1,
						0
					],
					[
						142375,
						1,
						0
					],
					[
						142056.25,
						3,
						0
					],
					[
						142196.875,
						0,
						0
					],
					[
						142625,
						1,
						0
					],
					[
						142800,
						1,
						0
					],
					[
						143000,
						1,
						0
					],
					[
						142750,
						3,
						0
					],
					[
						142875,
						0,
						0
					],
					[
						143125,
						0,
						0
					],
					[
						143250,
						3,
						0
					],
					[
						143500,
						3,
						0
					],
					[
						143375,
						1,
						0
					],
					[
						143625,
						1,
						0
					],
					[
						143750,
						2,
						0
					],
					[
						142575,
						0,
						0
					],
					[
						142425,
						3,
						0
					]
				],
				"altAnim": false,
				"bpm": 150,
				"changeBPM": false,
				"mustHitSection": true
			},
			{
				"lengthInSteps": 16,
				"typeOfSection": 0,
				"sectionNotes": [
					[
						144071.875,
						1,
						0,
						"Mom Sing"
					],
					[
						144706.25,
						2,
						0,
						"Mom Sing"
					],
					[
						144943.75,
						2,
						0,
						"Mom Sing"
					],
					[
						145575,
						1,
						0,
						"Mom Sing"
					],
					[
						145696.875,
						0,
						0,
						"Mom Sing"
					],
					[
						145934.375,
						0,
						0,
						"Mom Sing"
					],
					[
						145750,
						1,
						0,
						"Mom Sing"
					],
					[
						145500,
						0,
						0,
						"Mom Sing"
					],
					[
						145250,
						0,
						0,
						"Mom Sing"
					],
					[
						145000,
						3,
						0,
						"Mom Sing"
					],
					[
						145125,
						2,
						0,
						"Mom Sing"
					],
					[
						145375,
						2,
						0,
						"Mom Sing"
					],
					[
						144750,
						0,
						0,
						"Mom Sing"
					],
					[
						144625,
						0,
						0,
						"Mom Sing"
					],
					[
						144500,
						1,
						0,
						"Mom Sing"
					],
					[
						144250,
						2,
						0,
						"Mom Sing"
					],
					[
						144375,
						3,
						0,
						"Mom Sing"
					],
					[
						144000,
						3,
						0,
						"Mom Sing"
					],
					[
						144125,
						0,
						0,
						"Mom Sing"
					]
				],
				"altAnim": false,
				"bpm": 150,
				"changeBPM": false,
				"mustHitSection": false
			},
			{
				"lengthInSteps": 16,
				"typeOfSection": 0,
				"sectionNotes": [
					[
						146000,
						0,
						0
					],
					[
						146125,
						1,
						0
					],
					[
						146200,
						3,
						0
					],
					[
						146250,
						1,
						0
					],
					[
						146375,
						0,
						0
					],
					[
						146500,
						1,
						0
					],
					[
						146625,
						1,
						0
					],
					[
						146571.875,
						3,
						0
					],
					[
						146750,
						0,
						0
					],
					[
						147000,
						0,
						0
					],
					[
						146875,
						3,
						0
					],
					[
						147250,
						3,
						0
					],
					[
						147500,
						1,
						0
					],
					[
						147750,
						2,
						0
					]
				],
				"altAnim": false,
				"bpm": 150,
				"changeBPM": false,
				"mustHitSection": true
			},
			{
				"lengthInSteps": 16,
				"typeOfSection": 0,
				"sectionNotes": [
					[
						148000,
						3,
						0
					],
					[
						148375,
						3,
						0
					],
					[
						148250,
						1,
						0
					],
					[
						148125,
						0,
						0
					],
					[
						148750,
						1,
						0
					],
					[
						148625,
						0,
						0
					],
					[
						148875,
						2,
						0
					],
					[
						149000,
						4,
						0
					],
					[
						149125,
						7,
						0
					],
					[
						149375,
						4,
						0
					],
					[
						149250,
						5,
						0
					],
					[
						149625,
						7,
						0
					],
					[
						149750,
						5,
						0
					],
					[
						149875,
						6,
						0
					]
				],
				"altAnim": false,
				"bpm": 150,
				"changeBPM": false,
				"mustHitSection": false
			},
			{
				"lengthInSteps": 16,
				"typeOfSection": 0,
				"sectionNotes": [
					[
						151000,
						3,
						0
					],
					[
						151125,
						1,
						0
					],
					[
						151250,
						2,
						0
					],
					[
						151375,
						3,
						0
					],
					[
						151500,
						1,
						0
					],
					[
						151625,
						0,
						0
					],
					[
						151750,
						1,
						0
					],
					[
						151875,
						2,
						0
					],
					[
						150000,
						7,
						0,
						"Mom Sing"
					],
					[
						150125,
						5,
						0,
						"Mom Sing"
					],
					[
						150250,
						6,
						0,
						"Mom Sing"
					],
					[
						150375,
						5,
						0,
						"Mom Sing"
					],
					[
						150500,
						6,
						0,
						"Mom Sing"
					],
					[
						150625,
						5,
						0,
						"Mom Sing"
					],
					[
						150750,
						4,
						0,
						"Mom Sing"
					],
					[
						150875,
						5,
						0,
						"Mom Sing"
					]
				],
				"altAnim": false,
				"bpm": 150,
				"changeBPM": false,
				"mustHitSection": true
			},
			{
				"lengthInSteps": 16,
				"typeOfSection": 0,
				"sectionNotes": [
					[
						152000,
						3,
						0
					],
					[
						152125,
						0,
						0
					],
					[
						152250,
						1,
						0
					],
					[
						152375,
						2,
						0
					],
					[
						152500,
						4,
						0
					],
					[
						152625,
						7,
						0
					],
					[
						152750,
						5,
						0
					],
					[
						152875,
						6,
						0
					],
					[
						153500,
						4,
						0
					],
					[
						153625,
						7,
						0
					],
					[
						153750,
						5,
						0
					],
					[
						153875,
						6,
						0
					],
					[
						153375,
						2,
						0,
						"Mom Sing"
					],
					[
						153250,
						1,
						0,
						"Mom Sing"
					],
					[
						153125,
						0,
						0,
						"Mom Sing"
					],
					[
						153000,
						3,
						0,
						"Mom Sing"
					]
				],
				"altAnim": false,
				"bpm": 150,
				"changeBPM": false,
				"mustHitSection": false
			},
			{
				"lengthInSteps": 16,
				"typeOfSection": 0,
				"sectionNotes": [
					[
						154000,
						3,
						0
					],
					[
						154125,
						1,
						0
					],
					[
						154250,
						4,
						0
					],
					[
						154375,
						5,
						0
					],
					[
						154750,
						4,
						0
					],
					[
						154875,
						5,
						0
					],
					[
						155000,
						4,
						750
					],
					[
						155875,
						5,
						0
					],
					[
						154500,
						3,
						0,
						"Mom Sing"
					],
					[
						154625,
						1,
						0,
						"Mom Sing"
					],
					[
						155000,
						3,
						750,
						"Duo Note"
					],
					[
						155875,
						1,
						0,
						"Duo Note"
					]
				],
				"altAnim": false,
				"bpm": 150,
				"changeBPM": false,
				"mustHitSection": false
			},
			{
				"lengthInSteps": 16,
				"typeOfSection": 0,
				"sectionNotes": [],
				"altAnim": false,
				"bpm": 150,
				"changeBPM": false,
				"mustHitSection": false
			},
			{
				"lengthInSteps": 16,
				"typeOfSection": 0,
				"sectionNotes": [],
				"altAnim": false,
				"bpm": 150,
				"changeBPM": false,
				"mustHitSection": true
			},
			{
				"lengthInSteps": 16,
				"typeOfSection": 0,
				"sectionNotes": [],
				"altAnim": false,
				"bpm": 150,
				"changeBPM": false,
				"mustHitSection": true
			},
			{
				"lengthInSteps": 16,
				"typeOfSection": 0,
				"sectionNotes": [],
				"altAnim": false,
				"bpm": 150,
				"changeBPM": false,
				"mustHitSection": false
			},
			{
				"lengthInSteps": 16,
				"typeOfSection": 0,
				"sectionNotes": [],
				"altAnim": false,
				"bpm": 150,
				"changeBPM": false,
				"mustHitSection": false
			},
			{
				"lengthInSteps": 16,
				"typeOfSection": 0,
				"sectionNotes": [],
				"altAnim": false,
				"bpm": 150,
				"changeBPM": false,
				"mustHitSection": false
			},
			{
				"lengthInSteps": 16,
				"typeOfSection": 0,
				"sectionNotes": [],
				"altAnim": false,
				"bpm": 150,
				"changeBPM": false,
				"mustHitSection": false
			},
			{
				"lengthInSteps": 16,
				"typeOfSection": 0,
				"sectionNotes": [],
				"altAnim": false,
				"bpm": 150,
				"changeBPM": false,
				"mustHitSection": true
			},
			{
				"lengthInSteps": 16,
				"typeOfSection": 0,
				"sectionNotes": [],
				"altAnim": false,
				"bpm": 150,
				"changeBPM": false,
				"mustHitSection": true
			},
			{
				"lengthInSteps": 16,
				"typeOfSection": 0,
				"sectionNotes": [],
				"altAnim": false,
				"bpm": 150,
				"changeBPM": false,
				"mustHitSection": true
			},
			{
				"lengthInSteps": 16,
				"typeOfSection": 0,
				"sectionNotes": [],
				"altAnim": false,
				"bpm": 150,
				"changeBPM": false,
				"mustHitSection": true
			},
			{
				"lengthInSteps": 16,
				"typeOfSection": 0,
				"sectionNotes": [],
				"altAnim": false,
				"bpm": 150,
				"changeBPM": true,
				"mustHitSection": false
			},
			{
				"lengthInSteps": 16,
				"typeOfSection": 0,
				"sectionNotes": [],
				"altAnim": false,
				"bpm": 150,
				"changeBPM": false,
				"mustHitSection": false
			},
			{
				"lengthInSteps": 16,
				"typeOfSection": 0,
				"sectionNotes": [],
				"altAnim": false,
				"bpm": 150,
				"changeBPM": false,
				"mustHitSection": false
			},
			{
				"lengthInSteps": 16,
				"typeOfSection": 0,
				"sectionNotes": [],
				"altAnim": false,
				"bpm": 150,
				"changeBPM": false,
				"mustHitSection": false
			},
			{
				"lengthInSteps": 16,
				"typeOfSection": 0,
				"sectionNotes": [],
				"altAnim": false,
				"bpm": 150,
				"changeBPM": false,
				"mustHitSection": true
			},
			{
				"lengthInSteps": 16,
				"typeOfSection": 0,
				"sectionNotes": [],
				"altAnim": false,
				"bpm": 150,
				"changeBPM": false,
				"mustHitSection": true
			},
			{
				"lengthInSteps": 16,
				"typeOfSection": 0,
				"sectionNotes": [],
				"altAnim": false,
				"bpm": 150,
				"changeBPM": false,
				"mustHitSection": true
			},
			{
				"lengthInSteps": 16,
				"typeOfSection": 0,
				"sectionNotes": [],
				"altAnim": false,
				"bpm": 150,
				"changeBPM": false,
				"mustHitSection": true
			},
			{
				"lengthInSteps": 16,
				"typeOfSection": 0,
				"sectionNotes": [],
				"altAnim": false,
				"bpm": 150,
				"changeBPM": false,
				"mustHitSection": false
			},
			{
				"lengthInSteps": 16,
				"typeOfSection": 0,
				"sectionNotes": [],
				"altAnim": false,
				"bpm": 150,
				"changeBPM": false,
				"mustHitSection": false
			},
			{
				"lengthInSteps": 16,
				"typeOfSection": 0,
				"sectionNotes": [],
				"altAnim": false,
				"bpm": 150,
				"changeBPM": false,
				"mustHitSection": false
			},
			{
				"lengthInSteps": 16,
				"typeOfSection": 0,
				"sectionNotes": [],
				"altAnim": false,
				"bpm": 150,
				"changeBPM": false,
				"mustHitSection": false
			},
			{
				"sectionNotes": [],
				"typeOfSection": 0,
				"lengthInSteps": 16,
				"altAnim": false,
				"mustHitSection": true,
				"changeBPM": false,
				"bpm": 150
			},
			{
				"sectionNotes": [],
				"typeOfSection": 0,
				"lengthInSteps": 16,
				"altAnim": false,
				"mustHitSection": true,
				"changeBPM": false,
				"bpm": 144
			},
			{
				"sectionNotes": [],
				"typeOfSection": 0,
				"lengthInSteps": 16,
				"altAnim": false,
				"mustHitSection": true,
				"changeBPM": false,
				"bpm": 144
			},
			{
				"sectionNotes": [],
				"typeOfSection": 0,
				"lengthInSteps": 16,
				"altAnim": false,
				"mustHitSection": true,
				"changeBPM": false,
				"bpm": 144
			},
			{
				"sectionNotes": [],
				"typeOfSection": 0,
				"lengthInSteps": 16,
				"altAnim": false,
				"mustHitSection": false,
				"changeBPM": false,
				"bpm": 144
			},
			{
				"sectionNotes": [],
				"typeOfSection": 0,
				"lengthInSteps": 16,
				"altAnim": false,
				"mustHitSection": false,
				"changeBPM": false,
				"bpm": 144
			},
			{
				"sectionNotes": [],
				"typeOfSection": 0,
				"lengthInSteps": 16,
				"altAnim": false,
				"mustHitSection": true,
				"changeBPM": false,
				"bpm": 144
			},
			{
				"sectionNotes": [],
				"typeOfSection": 0,
				"lengthInSteps": 16,
				"altAnim": false,
				"mustHitSection": true,
				"changeBPM": false,
				"bpm": 144
			},
			{
				"sectionNotes": [],
				"typeOfSection": 0,
				"lengthInSteps": 16,
				"altAnim": false,
				"mustHitSection": false,
				"changeBPM": false,
				"bpm": 144
			},
			{
				"sectionNotes": [],
				"typeOfSection": 0,
				"lengthInSteps": 16,
				"altAnim": false,
				"mustHitSection": false,
				"changeBPM": false,
				"bpm": 144
			},
			{
				"sectionNotes": [],
				"typeOfSection": 0,
				"lengthInSteps": 16,
				"altAnim": false,
				"mustHitSection": true,
				"changeBPM": false,
				"bpm": 144
			},
			{
				"sectionNotes": [],
				"typeOfSection": 0,
				"lengthInSteps": 16,
				"altAnim": false,
				"mustHitSection": true,
				"changeBPM": false,
				"bpm": 144
			},
			{
				"sectionNotes": [],
				"typeOfSection": 0,
				"lengthInSteps": 16,
				"altAnim": false,
				"mustHitSection": false,
				"changeBPM": false,
				"bpm": 144
			},
			{
				"sectionNotes": [],
				"typeOfSection": 0,
				"lengthInSteps": 16,
				"altAnim": false,
				"mustHitSection": false,
				"changeBPM": false,
				"bpm": 144
			},
			{
				"sectionNotes": [],
				"typeOfSection": 0,
				"lengthInSteps": 16,
				"altAnim": false,
				"mustHitSection": false,
				"changeBPM": false,
				"bpm": 144
			},
			{
				"sectionNotes": [],
				"typeOfSection": 0,
				"lengthInSteps": 16,
				"altAnim": false,
				"mustHitSection": false,
				"changeBPM": false,
				"bpm": 144
			},
			{
				"sectionNotes": [],
				"typeOfSection": 0,
				"lengthInSteps": 16,
				"altAnim": false,
				"mustHitSection": true,
				"changeBPM": false,
				"bpm": 144
			},
			{
				"sectionNotes": [],
				"typeOfSection": 0,
				"lengthInSteps": 16,
				"altAnim": false,
				"mustHitSection": true,
				"changeBPM": false,
				"bpm": 144
			},
			{
				"sectionNotes": [],
				"typeOfSection": 0,
				"lengthInSteps": 16,
				"altAnim": false,
				"mustHitSection": true,
				"changeBPM": false,
				"bpm": 144
			},
			{
				"sectionNotes": [],
				"typeOfSection": 0,
				"lengthInSteps": 16,
				"altAnim": false,
				"mustHitSection": true,
				"changeBPM": false,
				"bpm": 144
			},
			{
				"sectionNotes": [],
				"typeOfSection": 0,
				"lengthInSteps": 16,
				"altAnim": false,
				"mustHitSection": false,
				"changeBPM": false,
				"bpm": 144
			},
			{
				"sectionNotes": [],
				"typeOfSection": 0,
				"lengthInSteps": 16,
				"altAnim": false,
				"mustHitSection": false,
				"changeBPM": false,
				"bpm": 144
			},
			{
				"lengthInSteps": 16,
				"typeOfSection": 0,
				"sectionNotes": [],
				"altAnim": false,
				"bpm": 144,
				"changeBPM": false,
				"mustHitSection": true
			},
			{
				"lengthInSteps": 16,
				"typeOfSection": 0,
				"sectionNotes": [],
				"altAnim": false,
				"bpm": 144,
				"changeBPM": false,
				"mustHitSection": true
			},
			{
				"sectionNotes": [],
				"typeOfSection": 0,
				"lengthInSteps": 16,
				"altAnim": false,
				"mustHitSection": true,
				"changeBPM": false,
				"bpm": 144
			},
			{
				"lengthInSteps": 16,
				"typeOfSection": 0,
				"sectionNotes": [],
				"altAnim": false,
				"gfSection": false,
				"bpm": 120,
				"changeBPM": false,
				"mustHitSection": true
			},
			{
				"sectionNotes": [],
				"typeOfSection": 0,
				"lengthInSteps": 16,
				"gfSection": false,
				"altAnim": false,
				"mustHitSection": true,
				"changeBPM": false,
				"bpm": 120
			},
			{
				"gfSection": false,
				"altAnim": false,
				"typeOfSection": 0,
				"sectionNotes": [],
				"bpm": 120,
				"sectionBeats": 4,
				"changeBPM": false,
				"mustHitSection": true
			}
		],
		"player2": "Ash",
		"player3": null,
		"player4": "Cerbera",
		"song": "Intertwined",
		"stage": "Glitch",
		"arrowSkin": "Custom Notes/Void",
		"needsVoices": true,
		"validScore": true,
		"bpm": 120,
		"speed": 3,
		"gameHUDType": "B3 Remix"
	}
}